{"Meta Data": {"1. Information": "Daily Prices (open, high, low, close) and Volumes", "2. Symbol": "EVGO", "3. Last Refreshed": "2022-02-07", "4. Output Size": "Full size", "5. Time Zone": "US/Eastern"}, "Time Series (Daily)": {"2022-02-07": {"1. open": "8.0488", "2. high": "8.1400", "3. low": "7.7900", "4. close": "8.1400", "5. volume": "1455553"}, "2022-02-04": {"1. open": "7.8200", "2. high": "8.1400", "3. low": "7.5000", "4. close": "7.9000", "5. volume": "2066841"}, "2022-02-03": {"1. open": "8.0000", "2. high": "8.2100", "3. low": "7.6600", "4. close": "7.6700", "5. volume": "2032670"}, "2022-02-02": {"1. open": "8.6765", "2. high": "8.6765", "3. low": "8.0700", "4. close": "8.1800", "5. volume": "2784845"}, "2022-02-01": {"1. open": "8.4600", "2. high": "8.8700", "3. low": "8.0214", "4. close": "8.5100", "5. volume": "3191620"}, "2022-01-31": {"1. open": "7.4500", "2. high": "8.2500", "3. low": "7.3600", "4. close": "8.2500", "5. volume": "2418375"}, "2022-01-28": {"1. open": "7.3000", "2. high": "7.6000", "3. low": "7.0800", "4. close": "7.4600", "5. volume": "2996399"}, "2022-01-27": {"1. open": "7.6865", "2. high": "7.8400", "3. low": "7.3000", "4. close": "7.3700", "5. volume": "1748679"}, "2022-01-26": {"1. open": "8.2000", "2. high": "8.2000", "3. low": "7.4500", "4. close": "7.5100", "5. volume": "3269082"}, "2022-01-25": {"1. open": "7.8600", "2. high": "8.0800", "3. low": "7.6900", "4. close": "7.9200", "5. volume": "2152878"}, "2022-01-24": {"1. open": "7.4550", "2. high": "8.3300", "3. low": "7.0000", "4. close": "8.3200", "5. volume": "4841567"}, "2022-01-21": {"1. open": "8.0300", "2. high": "8.1900", "3. low": "7.7000", "4. close": "7.9900", "5. volume": "2961521"}, "2022-01-20": {"1. open": "8.2600", "2. high": "8.7899", "3. low": "8.1800", "4. close": "8.2000", "5. volume": "2245393"}, "2022-01-19": {"1. open": "8.2800", "2. high": "8.4700", "3. low": "8.1100", "4. close": "8.3400", "5. volume": "2154150"}, "2022-01-18": {"1. open": "8.3450", "2. high": "8.5300", "3. low": "8.1000", "4. close": "8.2400", "5. volume": "4309866"}, "2022-01-14": {"1. open": "8.6900", "2. high": "9.0350", "3. low": "8.2400", "4. close": "8.5900", "5. volume": "4071659"}, "2022-01-13": {"1. open": "9.2900", "2. high": "9.4335", "3. low": "8.7750", "4. close": "8.8100", "5. volume": "3424576"}, "2022-01-12": {"1. open": "9.7600", "2. high": "9.8300", "3. low": "9.2500", "4. close": "9.3000", "5. volume": "2453409"}, "2022-01-11": {"1. open": "9.1700", "2. high": "9.6500", "3. low": "9.0800", "4. close": "9.6000", "5. volume": "2873957"}, "2022-01-10": {"1. open": "9.3438", "2. high": "9.3850", "3. low": "8.7500", "4. close": "9.1700", "5. volume": "4564004"}, "2022-01-07": {"1. open": "9.7500", "2. high": "10.1800", "3. low": "9.3500", "4. close": "9.5200", "5. volume": "3360689"}, "2022-01-06": {"1. open": "9.6200", "2. high": "9.9550", "3. low": "8.9700", "4. close": "9.5800", "5. volume": "4630562"}, "2022-01-05": {"1. open": "10.0500", "2. high": "10.3200", "3. low": "9.5400", "4. close": "9.5600", "5. volume": "3808803"}, "2022-01-04": {"1. open": "10.7000", "2. high": "10.7500", "3. low": "9.8600", "4. close": "10.1500", "5. volume": "4425808"}, "2022-01-03": {"1. open": "10.2400", "2. high": "10.8499", "3. low": "10.1600", "4. close": "10.6200", "5. volume": "4536353"}, "2021-12-31": {"1. open": "10.3720", "2. high": "10.7700", "3. low": "9.8600", "4. close": "9.9400", "5. volume": "3475682"}, "2021-12-30": {"1. open": "9.3400", "2. high": "10.6700", "3. low": "9.3351", "4. close": "10.2100", "5. volume": "7658294"}, "2021-12-29": {"1. open": "9.6600", "2. high": "9.7080", "3. low": "8.8600", "4. close": "9.3600", "5. volume": "4663971"}, "2021-12-28": {"1. open": "9.9500", "2. high": "10.0000", "3. low": "9.6000", "4. close": "9.7500", "5. volume": "3766152"}, "2021-12-27": {"1. open": "10.5500", "2. high": "10.6000", "3. low": "9.7900", "4. close": "10.0500", "5. volume": "4301140"}, "2021-12-23": {"1. open": "9.9050", "2. high": "10.6200", "3. low": "9.7100", "4. close": "10.4700", "5. volume": "4367867"}, "2021-12-22": {"1. open": "10.3000", "2. high": "10.3500", "3. low": "9.6200", "4. close": "9.9800", "5. volume": "3971725"}, "2021-12-21": {"1. open": "10.2200", "2. high": "10.5700", "3. low": "10.0300", "4. close": "10.3000", "5. volume": "3457577"}, "2021-12-20": {"1. open": "10.0900", "2. high": "10.2400", "3. low": "9.5100", "4. close": "9.9800", "5. volume": "6221067"}, "2021-12-17": {"1. open": "10.3300", "2. high": "10.9500", "3. low": "9.9600", "4. close": "10.5300", "5. volume": "7555096"}, "2021-12-16": {"1. open": "11.4300", "2. high": "11.4800", "3. low": "10.4600", "4. close": "10.5700", "5. volume": "5091603"}, "2021-12-15": {"1. open": "11.0800", "2. high": "11.4300", "3. low": "10.3300", "4. close": "11.1600", "5. volume": "5282569"}, "2021-12-14": {"1. open": "11.7000", "2. high": "11.7700", "3. low": "10.8500", "4. close": "11.0600", "5. volume": "5003717"}, "2021-12-13": {"1. open": "12.2736", "2. high": "12.8100", "3. low": "11.8400", "4. close": "12.0600", "5. volume": "4447521"}, "2021-12-10": {"1. open": "13.2100", "2. high": "13.2100", "3. low": "12.0400", "4. close": "12.3100", "5. volume": "6251194"}, "2021-12-09": {"1. open": "13.6750", "2. high": "13.7600", "3. low": "12.6000", "4. close": "12.8400", "5. volume": "17456042"}, "2021-12-08": {"1. open": "11.6550", "2. high": "12.2300", "3. low": "11.2000", "4. close": "12.1700", "5. volume": "2552711"}, "2021-12-07": {"1. open": "12.0350", "2. high": "12.4900", "3. low": "11.4800", "4. close": "11.6200", "5. volume": "4211941"}, "2021-12-06": {"1. open": "11.0150", "2. high": "11.4800", "3. low": "10.4400", "4. close": "11.2500", "5. volume": "3133463"}, "2021-12-03": {"1. open": "11.9100", "2. high": "11.9100", "3. low": "11.0200", "4. close": "11.1800", "5. volume": "3750330"}, "2021-12-02": {"1. open": "11.7600", "2. high": "12.0760", "3. low": "11.3216", "4. close": "11.7900", "5. volume": "3375372"}, "2021-12-01": {"1. open": "12.7000", "2. high": "13.1200", "3. low": "11.7200", "4. close": "11.7700", "5. volume": "4845437"}, "2021-11-30": {"1. open": "12.7076", "2. high": "13.2698", "3. low": "12.1500", "4. close": "12.5300", "5. volume": "3987542"}, "2021-11-29": {"1. open": "13.8500", "2. high": "14.0900", "3. low": "12.6500", "4. close": "12.9500", "5. volume": "4167444"}, "2021-11-26": {"1. open": "12.7900", "2. high": "13.7600", "3. low": "12.7600", "4. close": "13.6900", "5. volume": "1737519"}, "2021-11-24": {"1. open": "13.3700", "2. high": "13.8000", "3. low": "13.1140", "4. close": "13.5700", "5. volume": "2608792"}, "2021-11-23": {"1. open": "13.5600", "2. high": "14.6500", "3. low": "13.3100", "4. close": "13.6700", "5. volume": "4621504"}, "2021-11-22": {"1. open": "14.8100", "2. high": "14.9299", "3. low": "13.4300", "4. close": "13.7300", "5. volume": "6598718"}, "2021-11-19": {"1. open": "14.1100", "2. high": "15.1500", "3. low": "14.1100", "4. close": "14.7200", "5. volume": "4707338"}, "2021-11-18": {"1. open": "15.3300", "2. high": "15.4700", "3. low": "14.0000", "4. close": "14.5800", "5. volume": "8224659"}, "2021-11-17": {"1. open": "14.8100", "2. high": "16.7099", "3. low": "14.7100", "4. close": "15.7000", "5. volume": "12612935"}, "2021-11-16": {"1. open": "15.4600", "2. high": "15.9400", "3. low": "14.5800", "4. close": "15.2900", "5. volume": "13045982"}, "2021-11-15": {"1. open": "18.0000", "2. high": "18.1100", "3. low": "15.7700", "4. close": "16.1900", "5. volume": "21176558"}, "2021-11-12": {"1. open": "18.8750", "2. high": "19.5700", "3. low": "17.5300", "4. close": "18.9000", "5. volume": "22763666"}, "2021-11-11": {"1. open": "16.2800", "2. high": "19.5888", "3. low": "15.6000", "4. close": "19.2300", "5. volume": "62581135"}, "2021-11-10": {"1. open": "14.1600", "2. high": "17.2700", "3. low": "14.0300", "4. close": "15.4100", "5. volume": "48908836"}, "2021-11-09": {"1. open": "17.6250", "2. high": "17.7600", "3. low": "14.1800", "4. close": "14.8000", "5. volume": "88177743"}, "2021-11-08": {"1. open": "12.1050", "2. high": "14.4000", "3. low": "11.1200", "4. close": "13.4300", "5. volume": "53956011"}, "2021-11-05": {"1. open": "10.0828", "2. high": "10.3000", "3. low": "9.8114", "4. close": "9.9800", "5. volume": "2014126"}, "2021-11-04": {"1. open": "10.2500", "2. high": "10.3700", "3. low": "9.8300", "4. close": "9.9600", "5. volume": "2231975"}, "2021-11-03": {"1. open": "10.1700", "2. high": "10.5700", "3. low": "10.0200", "4. close": "10.1800", "5. volume": "2540864"}, "2021-11-02": {"1. open": "10.4600", "2. high": "10.5600", "3. low": "9.8400", "4. close": "10.3000", "5. volume": "3023073"}, "2021-11-01": {"1. open": "9.7100", "2. high": "10.3800", "3. low": "9.5800", "4. close": "10.3800", "5. volume": "3902027"}, "2021-10-29": {"1. open": "9.3500", "2. high": "9.4806", "3. low": "9.0100", "4. close": "9.3200", "5. volume": "2581665"}, "2021-10-28": {"1. open": "8.3500", "2. high": "9.4000", "3. low": "8.3300", "4. close": "9.2500", "5. volume": "4554733"}, "2021-10-27": {"1. open": "8.4400", "2. high": "8.8641", "3. low": "8.2700", "4. close": "8.3400", "5. volume": "3442455"}, "2021-10-26": {"1. open": "8.6200", "2. high": "8.7186", "3. low": "8.2100", "4. close": "8.2900", "5. volume": "4347400"}, "2021-10-25": {"1. open": "7.8700", "2. high": "8.7700", "3. low": "7.8100", "4. close": "8.6000", "5. volume": "4484935"}, "2021-10-22": {"1. open": "8.1200", "2. high": "8.2400", "3. low": "7.7300", "4. close": "7.8500", "5. volume": "1869273"}, "2021-10-21": {"1. open": "7.9500", "2. high": "8.1700", "3. low": "7.8500", "4. close": "8.1700", "5. volume": "1473452"}, "2021-10-20": {"1. open": "8.1446", "2. high": "8.1900", "3. low": "7.8990", "4. close": "7.9400", "5. volume": "1175256"}, "2021-10-19": {"1. open": "7.9064", "2. high": "8.2300", "3. low": "7.8300", "4. close": "8.1300", "5. volume": "1555244"}, "2021-10-18": {"1. open": "7.7700", "2. high": "7.9200", "3. low": "7.6400", "4. close": "7.8900", "5. volume": "1918980"}, "2021-10-15": {"1. open": "7.9500", "2. high": "7.9800", "3. low": "7.7600", "4. close": "7.8000", "5. volume": "1444544"}, "2021-10-14": {"1. open": "8.0400", "2. high": "8.0788", "3. low": "7.7950", "4. close": "7.9300", "5. volume": "1794437"}, "2021-10-13": {"1. open": "8.0400", "2. high": "8.1100", "3. low": "7.8350", "4. close": "8.1000", "5. volume": "1317723"}, "2021-10-12": {"1. open": "7.9800", "2. high": "8.1200", "3. low": "7.8600", "4. close": "8.0400", "5. volume": "1465736"}, "2021-10-11": {"1. open": "7.7453", "2. high": "8.1300", "3. low": "7.7100", "4. close": "7.8200", "5. volume": "1584112"}, "2021-10-08": {"1. open": "7.8000", "2. high": "7.9200", "3. low": "7.6200", "4. close": "7.6500", "5. volume": "1380219"}, "2021-10-07": {"1. open": "7.9400", "2. high": "8.0500", "3. low": "7.7200", "4. close": "7.7400", "5. volume": "1757706"}, "2021-10-06": {"1. open": "7.9300", "2. high": "8.1400", "3. low": "7.7400", "4. close": "7.8500", "5. volume": "2180909"}, "2021-10-05": {"1. open": "8.0500", "2. high": "8.1400", "3. low": "7.8300", "4. close": "8.0800", "5. volume": "1603240"}, "2021-10-04": {"1. open": "8.2000", "2. high": "8.2050", "3. low": "7.8300", "4. close": "7.9500", "5. volume": "1678138"}, "2021-10-01": {"1. open": "8.1500", "2. high": "8.3300", "3. low": "7.9300", "4. close": "8.2800", "5. volume": "1870761"}, "2021-09-30": {"1. open": "8.5000", "2. high": "8.5499", "3. low": "7.8700", "4. close": "8.1500", "5. volume": "3325267"}, "2021-09-29": {"1. open": "8.8800", "2. high": "9.1350", "3. low": "8.3400", "4. close": "8.3900", "5. volume": "8125943"}, "2021-09-28": {"1. open": "8.8300", "2. high": "9.2500", "3. low": "8.7200", "4. close": "8.7500", "5. volume": "4279261"}, "2021-09-27": {"1. open": "8.8000", "2. high": "9.1800", "3. low": "8.6700", "4. close": "9.0300", "5. volume": "2546546"}, "2021-09-24": {"1. open": "8.5200", "2. high": "8.9300", "3. low": "8.5200", "4. close": "8.7600", "5. volume": "4000069"}, "2021-09-23": {"1. open": "8.3000", "2. high": "8.7700", "3. low": "8.2500", "4. close": "8.6500", "5. volume": "3615205"}, "2021-09-22": {"1. open": "8.1400", "2. high": "8.2153", "3. low": "7.8100", "4. close": "8.1000", "5. volume": "3113805"}, "2021-09-21": {"1. open": "7.5700", "2. high": "8.0300", "3. low": "7.5020", "4. close": "7.8300", "5. volume": "4825130"}, "2021-09-20": {"1. open": "7.4500", "2. high": "7.5900", "3. low": "7.1700", "4. close": "7.2800", "5. volume": "2799490"}, "2021-09-17": {"1. open": "7.8400", "2. high": "7.9900", "3. low": "7.5600", "4. close": "7.5900", "5. volume": "7872613"}, "2021-09-16": {"1. open": "7.7500", "2. high": "7.9100", "3. low": "7.5100", "4. close": "7.8400", "5. volume": "2549583"}, "2021-09-15": {"1. open": "7.9900", "2. high": "8.0150", "3. low": "7.7000", "4. close": "7.7900", "5. volume": "2226264"}, "2021-09-14": {"1. open": "8.3000", "2. high": "8.4000", "3. low": "7.9000", "4. close": "7.9900", "5. volume": "3207306"}, "2021-09-13": {"1. open": "8.4300", "2. high": "8.4750", "3. low": "8.0600", "4. close": "8.2800", "5. volume": "2430124"}, "2021-09-10": {"1. open": "8.7600", "2. high": "8.8100", "3. low": "8.4100", "4. close": "8.4600", "5. volume": "1959731"}, "2021-09-09": {"1. open": "8.5000", "2. high": "8.8200", "3. low": "8.3600", "4. close": "8.7400", "5. volume": "1605299"}, "2021-09-08": {"1. open": "8.8300", "2. high": "8.8500", "3. low": "8.3500", "4. close": "8.4500", "5. volume": "2795174"}, "2021-09-07": {"1. open": "9.7100", "2. high": "9.7100", "3. low": "8.7400", "4. close": "8.8100", "5. volume": "4873243"}, "2021-09-03": {"1. open": "9.2000", "2. high": "9.5850", "3. low": "9.0100", "4. close": "9.5100", "5. volume": "2356832"}, "2021-09-02": {"1. open": "9.1000", "2. high": "9.3550", "3. low": "8.9100", "4. close": "9.2200", "5. volume": "2163935"}, "2021-09-01": {"1. open": "9.1000", "2. high": "9.2500", "3. low": "8.8700", "4. close": "8.8900", "5. volume": "1738415"}, "2021-08-31": {"1. open": "9.1300", "2. high": "9.2700", "3. low": "8.9400", "4. close": "9.1800", "5. volume": "1866527"}, "2021-08-30": {"1. open": "9.1100", "2. high": "9.2900", "3. low": "8.8500", "4. close": "9.1600", "5. volume": "1317598"}, "2021-08-27": {"1. open": "8.9500", "2. high": "9.0750", "3. low": "8.7300", "4. close": "9.0500", "5. volume": "2281282"}, "2021-08-26": {"1. open": "9.1000", "2. high": "9.1995", "3. low": "8.8500", "4. close": "8.9300", "5. volume": "1349120"}, "2021-08-25": {"1. open": "9.1700", "2. high": "9.4668", "3. low": "9.0200", "4. close": "9.0200", "5. volume": "1570782"}, "2021-08-24": {"1. open": "8.8000", "2. high": "9.2400", "3. low": "8.7900", "4. close": "9.2300", "5. volume": "2408010"}, "2021-08-23": {"1. open": "8.4900", "2. high": "8.8900", "3. low": "8.2600", "4. close": "8.8000", "5. volume": "2877949"}, "2021-08-20": {"1. open": "8.7000", "2. high": "8.7252", "3. low": "8.1200", "4. close": "8.4800", "5. volume": "3668816"}, "2021-08-19": {"1. open": "8.5200", "2. high": "8.9500", "3. low": "8.5000", "4. close": "8.7000", "5. volume": "2535582"}, "2021-08-18": {"1. open": "8.9700", "2. high": "8.9700", "3. low": "8.6000", "4. close": "8.6800", "5. volume": "2941589"}, "2021-08-17": {"1. open": "9.5500", "2. high": "9.5600", "3. low": "8.6100", "4. close": "8.7200", "5. volume": "5544687"}, "2021-08-16": {"1. open": "10.2800", "2. high": "10.2900", "3. low": "9.5400", "4. close": "9.5800", "5. volume": "3175823"}, "2021-08-13": {"1. open": "10.9000", "2. high": "11.0000", "3. low": "10.0900", "4. close": "10.3000", "5. volume": "3025673"}, "2021-08-12": {"1. open": "10.6268", "2. high": "11.1899", "3. low": "10.3501", "4. close": "11.0100", "5. volume": "2860408"}, "2021-08-11": {"1. open": "10.9300", "2. high": "10.9800", "3. low": "10.4900", "4. close": "10.7100", "5. volume": "2587998"}, "2021-08-10": {"1. open": "10.9942", "2. high": "11.2499", "3. low": "10.3700", "4. close": "10.7100", "5. volume": "4542510"}, "2021-08-09": {"1. open": "10.3500", "2. high": "10.9800", "3. low": "10.1600", "4. close": "10.7400", "5. volume": "4102022"}, "2021-08-06": {"1. open": "10.4000", "2. high": "10.4800", "3. low": "9.9100", "4. close": "10.2500", "5. volume": "3033659"}, "2021-08-05": {"1. open": "9.5000", "2. high": "10.4000", "3. low": "9.4500", "4. close": "10.0100", "5. volume": "7167593"}, "2021-08-04": {"1. open": "9.1100", "2. high": "9.6500", "3. low": "8.7700", "4. close": "9.1000", "5. volume": "4281333"}, "2021-08-03": {"1. open": "10.1400", "2. high": "10.1900", "3. low": "9.0200", "4. close": "9.1150", "5. volume": "7923093"}, "2021-08-02": {"1. open": "11.5400", "2. high": "11.6000", "3. low": "9.9500", "4. close": "9.9600", "5. volume": "10747909"}, "2021-07-30": {"1. open": "11.7000", "2. high": "12.3000", "3. low": "11.6000", "4. close": "11.8800", "5. volume": "682172"}, "2021-07-29": {"1. open": "12.3000", "2. high": "12.4500", "3. low": "11.8000", "4. close": "11.9500", "5. volume": "1197065"}, "2021-07-28": {"1. open": "11.4000", "2. high": "12.4500", "3. low": "11.2000", "4. close": "12.1900", "5. volume": "1252030"}, "2021-07-27": {"1. open": "11.8500", "2. high": "12.1200", "3. low": "11.1100", "4. close": "11.2600", "5. volume": "843367"}, "2021-07-26": {"1. open": "11.9000", "2. high": "12.0200", "3. low": "11.4200", "4. close": "11.5500", "5. volume": "739965"}, "2021-07-23": {"1. open": "12.2300", "2. high": "12.6500", "3. low": "11.6900", "4. close": "11.7400", "5. volume": "765995"}, "2021-07-22": {"1. open": "12.4100", "2. high": "12.7894", "3. low": "12.2300", "4. close": "12.3800", "5. volume": "837646"}, "2021-07-21": {"1. open": "12.8000", "2. high": "12.9800", "3. low": "12.1900", "4. close": "12.4400", "5. volume": "1243516"}, "2021-07-20": {"1. open": "11.5000", "2. high": "12.9390", "3. low": "11.4865", "4. close": "12.8900", "5. volume": "1913767"}, "2021-07-19": {"1. open": "11.5000", "2. high": "11.5500", "3. low": "10.7600", "4. close": "11.4700", "5. volume": "1540674"}, "2021-07-16": {"1. open": "12.2200", "2. high": "12.6700", "3. low": "11.5800", "4. close": "11.7700", "5. volume": "1571921"}, "2021-07-15": {"1. open": "10.9500", "2. high": "13.5000", "3. low": "10.4000", "4. close": "12.0800", "5. volume": "10502305"}, "2021-07-14": {"1. open": "11.5800", "2. high": "11.8200", "3. low": "10.5500", "4. close": "10.5800", "5. volume": "2141316"}, "2021-07-13": {"1. open": "12.0000", "2. high": "12.1790", "3. low": "11.3100", "4. close": "11.3700", "5. volume": "1184151"}, "2021-07-12": {"1. open": "12.2000", "2. high": "12.2900", "3. low": "11.7300", "4. close": "11.8300", "5. volume": "985805"}, "2021-07-09": {"1. open": "12.8600", "2. high": "12.8800", "3. low": "11.8700", "4. close": "11.9300", "5. volume": "2419988"}, "2021-07-08": {"1. open": "13.0400", "2. high": "13.1999", "3. low": "12.4300", "4. close": "12.5200", "5. volume": "1815337"}, "2021-07-07": {"1. open": "14.4000", "2. high": "14.6316", "3. low": "13.5000", "4. close": "13.7300", "5. volume": "1406259"}, "2021-07-06": {"1. open": "16.2100", "2. high": "16.2400", "3. low": "14.0000", "4. close": "14.5800", "5. volume": "1780451"}, "2021-07-02": {"1. open": "15.0000", "2. high": "16.1000", "3. low": "14.5000", "4. close": "15.1000", "5. volume": "4022069"}, "2021-07-01": {"1. open": "15.0500", "2. high": "15.1900", "3. low": "14.2430", "4. close": "14.3600", "5. volume": "700653"}, "2021-06-30": {"1. open": "15.6000", "2. high": "15.7399", "3. low": "14.7400", "4. close": "15.0200", "5. volume": "620737"}, "2021-06-29": {"1. open": "16.5000", "2. high": "16.5500", "3. low": "15.0400", "4. close": "15.3600", "5. volume": "950265"}, "2021-06-28": {"1. open": "16.4500", "2. high": "16.6400", "3. low": "15.6760", "4. close": "16.5000", "5. volume": "691083"}, "2021-06-25": {"1. open": "15.8700", "2. high": "16.4900", "3. low": "15.6200", "4. close": "16.1700", "5. volume": "944720"}, "2021-06-24": {"1. open": "15.4200", "2. high": "15.9422", "3. low": "15.0200", "4. close": "15.3900", "5. volume": "1088181"}, "2021-06-23": {"1. open": "14.2400", "2. high": "15.1300", "3. low": "14.1500", "4. close": "14.8300", "5. volume": "962435"}, "2021-06-22": {"1. open": "13.8700", "2. high": "13.9800", "3. low": "13.5100", "4. close": "13.9800", "5. volume": "278088"}, "2021-06-21": {"1. open": "14.0000", "2. high": "14.0500", "3. low": "13.5500", "4. close": "13.6900", "5. volume": "244791"}, "2021-06-18": {"1. open": "14.1300", "2. high": "14.3000", "3. low": "13.7100", "4. close": "14.0000", "5. volume": "332269"}, "2021-06-17": {"1. open": "14.4800", "2. high": "14.4800", "3. low": "13.9264", "4. close": "14.1100", "5. volume": "409435"}, "2021-06-16": {"1. open": "13.5450", "2. high": "14.4800", "3. low": "13.5200", "4. close": "14.4600", "5. volume": "593015"}, "2021-06-15": {"1. open": "13.6200", "2. high": "13.9200", "3. low": "13.4100", "4. close": "13.8100", "5. volume": "542529"}, "2021-06-14": {"1. open": "13.8000", "2. high": "14.1393", "3. low": "13.3600", "4. close": "13.6800", "5. volume": "573040"}, "2021-06-11": {"1. open": "14.0000", "2. high": "14.1100", "3. low": "13.6000", "4. close": "13.7300", "5. volume": "326569"}, "2021-06-10": {"1. open": "13.0900", "2. high": "13.8500", "3. low": "12.6000", "4. close": "13.7600", "5. volume": "495756"}, "2021-06-09": {"1. open": "13.9800", "2. high": "14.0700", "3. low": "12.7200", "4. close": "12.7900", "5. volume": "840315"}, "2021-06-08": {"1. open": "14.6300", "2. high": "14.8850", "3. low": "13.5600", "4. close": "13.7200", "5. volume": "768909"}, "2021-06-07": {"1. open": "13.9800", "2. high": "14.4900", "3. low": "13.8000", "4. close": "14.2300", "5. volume": "899869"}, "2021-06-04": {"1. open": "13.4600", "2. high": "14.1400", "3. low": "13.0500", "4. close": "14.0200", "5. volume": "952694"}, "2021-06-03": {"1. open": "11.8500", "2. high": "13.0500", "3. low": "11.8500", "4. close": "12.8800", "5. volume": "906817"}, "2021-06-02": {"1. open": "11.2900", "2. high": "12.6000", "3. low": "11.1000", "4. close": "12.0200", "5. volume": "1699971"}, "2021-06-01": {"1. open": "11.2200", "2. high": "11.3229", "3. low": "11.0900", "4. close": "11.2500", "5. volume": "475589"}, "2021-05-28": {"1. open": "11.4000", "2. high": "11.4000", "3. low": "11.0300", "4. close": "11.0800", "5. volume": "409451"}, "2021-05-27": {"1. open": "11.4800", "2. high": "11.4800", "3. low": "11.1100", "4. close": "11.1400", "5. volume": "337767"}, "2021-05-26": {"1. open": "11.1100", "2. high": "11.4800", "3. low": "11.0700", "4. close": "11.2500", "5. volume": "374623"}, "2021-05-25": {"1. open": "11.4500", "2. high": "11.4500", "3. low": "11.0000", "4. close": "11.1200", "5. volume": "238732"}, "2021-05-24": {"1. open": "11.2900", "2. high": "11.3800", "3. low": "11.0200", "4. close": "11.3300", "5. volume": "241942"}, "2021-05-21": {"1. open": "11.6800", "2. high": "11.6800", "3. low": "11.1500", "4. close": "11.2100", "5. volume": "188391"}, "2021-05-20": {"1. open": "11.4800", "2. high": "11.6900", "3. low": "11.4300", "4. close": "11.4700", "5. volume": "264526"}, "2021-05-19": {"1. open": "10.8500", "2. high": "11.4099", "3. low": "10.7100", "4. close": "11.2300", "5. volume": "457967"}, "2021-05-18": {"1. open": "10.9400", "2. high": "11.1300", "3. low": "10.8500", "4. close": "10.9700", "5. volume": "502725"}, "2021-05-17": {"1. open": "11.0000", "2. high": "11.2200", "3. low": "10.8500", "4. close": "10.9800", "5. volume": "275970"}, "2021-05-14": {"1. open": "10.9500", "2. high": "11.1000", "3. low": "10.8470", "4. close": "11.0500", "5. volume": "352345"}, "2021-05-13": {"1. open": "11.0600", "2. high": "11.1000", "3. low": "10.5500", "4. close": "10.7700", "5. volume": "543352"}, "2021-05-12": {"1. open": "11.0900", "2. high": "11.3500", "3. low": "11.0000", "4. close": "11.0500", "5. volume": "369289"}, "2021-05-11": {"1. open": "10.9300", "2. high": "11.4400", "3. low": "10.7727", "4. close": "11.1300", "5. volume": "497267"}, "2021-05-10": {"1. open": "11.7200", "2. high": "11.7200", "3. low": "11.1000", "4. close": "11.2200", "5. volume": "417207"}, "2021-05-07": {"1. open": "11.6400", "2. high": "11.7400", "3. low": "11.4300", "4. close": "11.6500", "5. volume": "239065"}, "2021-05-06": {"1. open": "11.7800", "2. high": "11.8800", "3. low": "11.1000", "4. close": "11.4300", "5. volume": "445879"}, "2021-05-05": {"1. open": "12.1100", "2. high": "12.2300", "3. low": "11.7500", "4. close": "11.7700", "5. volume": "194393"}, "2021-05-04": {"1. open": "12.1800", "2. high": "12.2533", "3. low": "11.6872", "4. close": "11.9900", "5. volume": "451194"}, "2021-05-03": {"1. open": "13.2800", "2. high": "13.2899", "3. low": "12.3800", "4. close": "12.3900", "5. volume": "576101"}, "2021-04-30": {"1. open": "13.0500", "2. high": "13.3133", "3. low": "12.8400", "4. close": "13.0500", "5. volume": "361400"}, "2021-04-29": {"1. open": "13.9900", "2. high": "14.0000", "3. low": "12.7000", "4. close": "13.1800", "5. volume": "623732"}, "2021-04-28": {"1. open": "12.6500", "2. high": "14.5700", "3. low": "12.5400", "4. close": "13.7000", "5. volume": "1579052"}, "2021-04-27": {"1. open": "13.2000", "2. high": "13.5000", "3. low": "12.6500", "4. close": "12.7200", "5. volume": "544019"}, "2021-04-26": {"1. open": "13.2700", "2. high": "13.6799", "3. low": "13.1100", "4. close": "13.1900", "5. volume": "598805"}, "2021-04-23": {"1. open": "13.1600", "2. high": "13.3680", "3. low": "13.0200", "4. close": "13.2000", "5. volume": "660121"}, "2021-04-22": {"1. open": "12.7700", "2. high": "13.3500", "3. low": "12.3500", "4. close": "12.6900", "5. volume": "1083250"}, "2021-04-21": {"1. open": "11.4300", "2. high": "12.1800", "3. low": "11.3400", "4. close": "12.1500", "5. volume": "577809"}, "2021-04-20": {"1. open": "11.7900", "2. high": "12.0633", "3. low": "11.1900", "4. close": "11.2700", "5. volume": "630448"}, "2021-04-19": {"1. open": "11.8400", "2. high": "11.8500", "3. low": "11.1500", "4. close": "11.7000", "5. volume": "1162027"}, "2021-04-16": {"1. open": "11.6000", "2. high": "11.6043", "3. low": "11.0200", "4. close": "11.0400", "5. volume": "815163"}, "2021-04-15": {"1. open": "12.2500", "2. high": "12.3000", "3. low": "11.3000", "4. close": "11.6200", "5. volume": "579099"}, "2021-04-14": {"1. open": "12.2000", "2. high": "12.3700", "3. low": "11.8700", "4. close": "12.0800", "5. volume": "669520"}, "2021-04-13": {"1. open": "12.7100", "2. high": "12.7500", "3. low": "11.8400", "4. close": "12.2000", "5. volume": "970536"}, "2021-04-12": {"1. open": "13.7000", "2. high": "13.7400", "3. low": "12.6000", "4. close": "12.8000", "5. volume": "805579"}, "2021-04-09": {"1. open": "13.6000", "2. high": "14.1500", "3. low": "13.6000", "4. close": "13.7300", "5. volume": "380321"}, "2021-04-08": {"1. open": "14.3400", "2. high": "14.3500", "3. low": "13.6750", "4. close": "13.7700", "5. volume": "438228"}, "2021-04-07": {"1. open": "13.8100", "2. high": "14.4600", "3. low": "13.5200", "4. close": "14.0000", "5. volume": "1056100"}, "2021-04-06": {"1. open": "13.1600", "2. high": "13.9635", "3. low": "13.1000", "4. close": "13.6800", "5. volume": "670792"}, "2021-04-05": {"1. open": "14.1000", "2. high": "14.4100", "3. low": "13.1000", "4. close": "13.1000", "5. volume": "1230616"}, "2021-04-01": {"1. open": "14.4500", "2. high": "14.5000", "3. low": "12.8200", "4. close": "13.6500", "5. volume": "1633660"}, "2021-03-31": {"1. open": "12.8000", "2. high": "13.7700", "3. low": "12.2500", "4. close": "13.7000", "5. volume": "1821482"}, "2021-03-30": {"1. open": "12.0100", "2. high": "12.7300", "3. low": "11.4500", "4. close": "12.4000", "5. volume": "1025509"}, "2021-03-29": {"1. open": "12.0000", "2. high": "12.4400", "3. low": "11.8300", "4. close": "12.2500", "5. volume": "729748"}, "2021-03-26": {"1. open": "11.8800", "2. high": "12.1600", "3. low": "11.3025", "4. close": "12.0200", "5. volume": "851524"}, "2021-03-25": {"1. open": "11.0000", "2. high": "11.6299", "3. low": "11.0000", "4. close": "11.5900", "5. volume": "854164"}, "2021-03-24": {"1. open": "12.4300", "2. high": "12.4500", "3. low": "11.1000", "4. close": "11.3200", "5. volume": "1124018"}, "2021-03-23": {"1. open": "12.3000", "2. high": "12.4600", "3. low": "12.0600", "4. close": "12.4300", "5. volume": "1119135"}, "2021-03-22": {"1. open": "12.2000", "2. high": "12.4000", "3. low": "11.9600", "4. close": "12.2700", "5. volume": "1039269"}, "2021-03-19": {"1. open": "12.0400", "2. high": "12.2200", "3. low": "11.5000", "4. close": "11.9000", "5. volume": "962903"}, "2021-03-18": {"1. open": "12.5000", "2. high": "12.5600", "3. low": "11.8000", "4. close": "11.8300", "5. volume": "1466726"}, "2021-03-17": {"1. open": "13.3100", "2. high": "13.3899", "3. low": "12.3700", "4. close": "12.6800", "5. volume": "1639740"}, "2021-03-16": {"1. open": "14.8500", "2. high": "14.9000", "3. low": "13.3100", "4. close": "13.3400", "5. volume": "937042"}, "2021-03-15": {"1. open": "14.7500", "2. high": "14.9900", "3. low": "13.9100", "4. close": "14.8200", "5. volume": "678221"}, "2021-03-12": {"1. open": "13.5000", "2. high": "15.0000", "3. low": "13.4000", "4. close": "14.5400", "5. volume": "825412"}, "2021-03-11": {"1. open": "13.2900", "2. high": "14.4100", "3. low": "13.1000", "4. close": "14.3600", "5. volume": "1332596"}, "2021-03-10": {"1. open": "14.0000", "2. high": "14.1800", "3. low": "12.8600", "4. close": "12.9200", "5. volume": "869973"}, "2021-03-09": {"1. open": "13.2800", "2. high": "13.7700", "3. low": "12.7500", "4. close": "13.6700", "5. volume": "760156"}, "2021-03-08": {"1. open": "12.9000", "2. high": "14.3300", "3. low": "11.8600", "4. close": "12.7000", "5. volume": "1368964"}, "2021-03-05": {"1. open": "12.1200", "2. high": "13.5000", "3. low": "10.5600", "4. close": "13.0500", "5. volume": "2681342"}, "2021-03-04": {"1. open": "12.6100", "2. high": "13.2000", "3. low": "11.5000", "4. close": "11.7800", "5. volume": "2235401"}, "2021-03-03": {"1. open": "14.6900", "2. high": "14.7817", "3. low": "13.0000", "4. close": "13.0300", "5. volume": "1602759"}, "2021-03-02": {"1. open": "15.2500", "2. high": "15.4000", "3. low": "14.4600", "4. close": "14.8000", "5. volume": "1088563"}, "2021-03-01": {"1. open": "16.7900", "2. high": "16.8000", "3. low": "14.9100", "4. close": "15.4800", "5. volume": "1445438"}, "2021-02-26": {"1. open": "15.0000", "2. high": "15.4900", "3. low": "13.7100", "4. close": "15.4800", "5. volume": "1287020"}, "2021-02-25": {"1. open": "16.0700", "2. high": "16.5200", "3. low": "14.9100", "4. close": "15.1000", "5. volume": "769707"}, "2021-02-24": {"1. open": "15.5000", "2. high": "16.6800", "3. low": "15.4500", "4. close": "16.4000", "5. volume": "1280719"}, "2021-02-23": {"1. open": "15.9300", "2. high": "15.9300", "3. low": "14.0000", "4. close": "14.7500", "5. volume": "2043733"}, "2021-02-22": {"1. open": "18.0900", "2. high": "18.4000", "3. low": "16.7600", "4. close": "16.9500", "5. volume": "945808"}, "2021-02-19": {"1. open": "18.1000", "2. high": "18.6400", "3. low": "18.0500", "4. close": "18.1000", "5. volume": "815311"}, "2021-02-18": {"1. open": "18.4900", "2. high": "18.5500", "3. low": "17.2800", "4. close": "17.7900", "5. volume": "1546406"}, "2021-02-17": {"1. open": "19.3200", "2. high": "19.3600", "3. low": "18.6000", "4. close": "18.9000", "5. volume": "1417756"}, "2021-02-16": {"1. open": "20.0000", "2. high": "20.1500", "3. low": "19.2850", "4. close": "19.5000", "5. volume": "1239648"}, "2021-02-12": {"1. open": "19.9100", "2. high": "20.6000", "3. low": "19.3500", "4. close": "20.0300", "5. volume": "1608134"}, "2021-02-11": {"1. open": "20.3000", "2. high": "20.5000", "3. low": "19.0900", "4. close": "19.3700", "5. volume": "2385717"}, "2021-02-10": {"1. open": "20.0500", "2. high": "20.1500", "3. low": "18.7200", "4. close": "19.0500", "5. volume": "2262039"}, "2021-02-09": {"1. open": "20.5500", "2. high": "20.7000", "3. low": "19.9000", "4. close": "20.1500", "5. volume": "1767620"}, "2021-02-08": {"1. open": "21.7100", "2. high": "21.7900", "3. low": "20.4000", "4. close": "20.5500", "5. volume": "2044923"}, "2021-02-05": {"1. open": "20.0300", "2. high": "21.5000", "3. low": "19.9000", "4. close": "21.2000", "5. volume": "2421022"}, "2021-02-04": {"1. open": "20.3000", "2. high": "20.4199", "3. low": "19.6900", "4. close": "19.7600", "5. volume": "1913448"}, "2021-02-03": {"1. open": "20.6500", "2. high": "20.8246", "3. low": "20.2000", "4. close": "20.3000", "5. volume": "1658349"}, "2021-02-02": {"1. open": "21.1100", "2. high": "21.3788", "3. low": "20.4989", "4. close": "20.6000", "5. volume": "1739678"}, "2021-02-01": {"1. open": "21.8500", "2. high": "21.9500", "3. low": "20.3801", "4. close": "20.9700", "5. volume": "1744827"}, "2021-01-29": {"1. open": "21.0000", "2. high": "21.5000", "3. low": "20.4000", "4. close": "20.9000", "5. volume": "2015529"}, "2021-01-28": {"1. open": "21.8300", "2. high": "21.8899", "3. low": "20.4000", "4. close": "20.9100", "5. volume": "3134586"}, "2021-01-27": {"1. open": "21.4600", "2. high": "23.5000", "3. low": "19.8000", "4. close": "20.1000", "5. volume": "6735798"}, "2021-01-26": {"1. open": "21.4900", "2. high": "24.3400", "3. low": "20.6701", "4. close": "22.0700", "5. volume": "11536657"}, "2021-01-25": {"1. open": "22.4900", "2. high": "23.5000", "3. low": "19.5000", "4. close": "19.6700", "5. volume": "10862090"}, "2021-01-22": {"1. open": "20.7500", "2. high": "24.0000", "3. low": "20.0000", "4. close": "22.0000", "5. volume": "49423953"}, "2021-01-21": {"1. open": "13.6500", "2. high": "13.7600", "3. low": "13.0000", "4. close": "13.3400", "5. volume": "327799"}, "2021-01-20": {"1. open": "14.1400", "2. high": "14.1400", "3. low": "13.4800", "4. close": "13.5800", "5. volume": "625040"}, "2021-01-19": {"1. open": "12.6200", "2. high": "15.0100", "3. low": "12.4700", "4. close": "13.2200", "5. volume": "1110017"}, "2021-01-15": {"1. open": "13.2000", "2. high": "13.2800", "3. low": "12.5400", "4. close": "12.5500", "5. volume": "214695"}, "2021-01-14": {"1. open": "13.1100", "2. high": "13.2500", "3. low": "12.8400", "4. close": "13.1000", "5. volume": "511991"}, "2021-01-13": {"1. open": "12.4000", "2. high": "13.3500", "3. low": "12.1050", "4. close": "12.8000", "5. volume": "535686"}, "2021-01-12": {"1. open": "11.5000", "2. high": "13.4900", "3. low": "11.3850", "4. close": "11.8900", "5. volume": "339977"}, "2021-01-11": {"1. open": "11.2600", "2. high": "11.5000", "3. low": "11.0000", "4. close": "11.5000", "5. volume": "143129"}, "2021-01-08": {"1. open": "11.3400", "2. high": "11.3400", "3. low": "10.8166", "4. close": "10.8300", "5. volume": "94514"}, "2021-01-07": {"1. open": "10.7100", "2. high": "11.0700", "3. low": "10.6001", "4. close": "10.9800", "5. volume": "121069"}, "2021-01-06": {"1. open": "10.6000", "2. high": "10.7100", "3. low": "10.4400", "4. close": "10.5500", "5. volume": "171812"}, "2021-01-05": {"1. open": "10.6000", "2. high": "10.6999", "3. low": "10.5000", "4. close": "10.5900", "5. volume": "49965"}, "2021-01-04": {"1. open": "10.9200", "2. high": "10.9200", "3. low": "10.5300", "4. close": "10.5300", "5. volume": "109850"}, "2020-12-31": {"1. open": "10.8100", "2. high": "10.8800", "3. low": "10.6000", "4. close": "10.7100", "5. volume": "46928"}, "2020-12-30": {"1. open": "10.7500", "2. high": "10.7700", "3. low": "10.6400", "4. close": "10.7400", "5. volume": "166733"}, "2020-12-29": {"1. open": "11.0100", "2. high": "11.0100", "3. low": "10.4800", "4. close": "10.7600", "5. volume": "181058"}, "2020-12-28": {"1. open": "11.2300", "2. high": "11.2400", "3. low": "10.8500", "4. close": "10.9500", "5. volume": "102837"}, "2020-12-24": {"1. open": "11.0000", "2. high": "11.3800", "3. low": "10.7600", "4. close": "10.9287", "5. volume": "362262"}, "2020-12-23": {"1. open": "10.7100", "2. high": "11.3200", "3. low": "10.6650", "4. close": "11.0252", "5. volume": "315376"}, "2020-12-22": {"1. open": "10.4600", "2. high": "10.8450", "3. low": "10.4600", "4. close": "10.6300", "5. volume": "83658"}, "2020-12-21": {"1. open": "10.5900", "2. high": "10.5900", "3. low": "10.5000", "4. close": "10.5300", "5. volume": "52035"}, "2020-12-18": {"1. open": "10.6300", "2. high": "10.6300", "3. low": "10.3500", "4. close": "10.4000", "5. volume": "50665"}, "2020-12-17": {"1. open": "10.4100", "2. high": "10.8000", "3. low": "10.4100", "4. close": "10.4800", "5. volume": "19769"}, "2020-12-16": {"1. open": "10.4000", "2. high": "10.5000", "3. low": "10.1500", "4. close": "10.4900", "5. volume": "75756"}, "2020-12-15": {"1. open": "10.6300", "2. high": "10.6600", "3. low": "10.1900", "4. close": "10.3600", "5. volume": "73583"}, "2020-12-14": {"1. open": "10.7400", "2. high": "10.7400", "3. low": "10.3500", "4. close": "10.5000", "5. volume": "63780"}, "2020-12-11": {"1. open": "10.2300", "2. high": "10.7600", "3. low": "10.2000", "4. close": "10.4900", "5. volume": "179861"}, "2020-12-10": {"1. open": "10.2600", "2. high": "10.2600", "3. low": "10.0400", "4. close": "10.1300", "5. volume": "68731"}, "2020-12-09": {"1. open": "10.0700", "2. high": "10.2500", "3. low": "10.0000", "4. close": "10.2000", "5. volume": "101633"}, "2020-12-08": {"1. open": "10.6900", "2. high": "10.6900", "3. low": "10.0400", "4. close": "10.0900", "5. volume": "75806"}, "2020-12-07": {"1. open": "10.3600", "2. high": "10.4500", "3. low": "9.9900", "4. close": "10.3100", "5. volume": "131700"}, "2020-12-04": {"1. open": "10.0400", "2. high": "10.3100", "3. low": "9.9900", "4. close": "10.1400", "5. volume": "142395"}, "2020-12-03": {"1. open": "10.0100", "2. high": "10.0200", "3. low": "9.9100", "4. close": "9.9100", "5. volume": "12243"}, "2020-12-02": {"1. open": "10.0500", "2. high": "10.1600", "3. low": "9.8800", "4. close": "10.0000", "5. volume": "15082"}, "2020-12-01": {"1. open": "10.0000", "2. high": "10.1000", "3. low": "10.0000", "4. close": "10.0894", "5. volume": "12966"}, "2020-11-30": {"1. open": "10.5300", "2. high": "10.9000", "3. low": "9.8800", "4. close": "9.9450", "5. volume": "178282"}, "2020-11-27": {"1. open": "10.0000", "2. high": "10.4300", "3. low": "9.9700", "4. close": "10.0300", "5. volume": "58166"}, "2020-11-25": {"1. open": "9.9753", "2. high": "9.9900", "3. low": "9.7900", "4. close": "9.9500", "5. volume": "16670"}, "2020-11-24": {"1. open": "10.4000", "2. high": "10.4000", "3. low": "9.7500", "4. close": "9.8000", "5. volume": "45888"}, "2020-11-23": {"1. open": "9.9000", "2. high": "10.4000", "3. low": "9.8900", "4. close": "9.8989", "5. volume": "12336"}, "2020-11-20": {"1. open": "9.7460", "2. high": "9.9322", "3. low": "9.7460", "4. close": "9.8114", "5. volume": "1082"}}}