{"Meta Data": {"1. Information": "Daily Prices (open, high, low, close) and Volumes", "2. Symbol": "ICOA", "3. Last Refreshed": "2022-02-07", "4. Output Size": "Full size", "5. Time Zone": "US/Eastern"}, "Time Series (Daily)": {"2022-02-07": {"1. open": "0.0052", "2. high": "0.0056", "3. low": "0.0049", "4. close": "0.0052", "5. volume": "63850800"}, "2022-02-04": {"1. open": "0.0049", "2. high": "0.0055", "3. low": "0.0046", "4. close": "0.0049", "5. volume": "103695347"}, "2022-02-03": {"1. open": "0.0050", "2. high": "0.0051", "3. low": "0.0047", "4. close": "0.0048", "5. volume": "56921261"}, "2022-02-02": {"1. open": "0.0051", "2. high": "0.0054", "3. low": "0.0047", "4. close": "0.0050", "5. volume": "67222223"}, "2022-02-01": {"1. open": "0.0058", "2. high": "0.0058", "3. low": "0.0049", "4. close": "0.0051", "5. volume": "102950902"}, "2022-01-31": {"1. open": "0.0058", "2. high": "0.0063", "3. low": "0.0056", "4. close": "0.0058", "5. volume": "30699176"}, "2022-01-28": {"1. open": "0.0054", "2. high": "0.0059", "3. low": "0.0052", "4. close": "0.0058", "5. volume": "47392158"}, "2022-01-27": {"1. open": "0.0056", "2. high": "0.0056", "3. low": "0.0052", "4. close": "0.0053", "5. volume": "29425138"}, "2022-01-26": {"1. open": "0.0057", "2. high": "0.0058", "3. low": "0.0052", "4. close": "0.0055", "5. volume": "54588318"}, "2022-01-25": {"1. open": "0.0059", "2. high": "0.0059", "3. low": "0.0053", "4. close": "0.0056", "5. volume": "43273179"}, "2022-01-24": {"1. open": "0.0064", "2. high": "0.0067", "3. low": "0.0050", "4. close": "0.0059", "5. volume": "111575394"}, "2022-01-21": {"1. open": "0.0057", "2. high": "0.0067", "3. low": "0.0053", "4. close": "0.0066", "5. volume": "128736864"}, "2022-01-20": {"1. open": "0.0062", "2. high": "0.0064", "3. low": "0.0058", "4. close": "0.0060", "5. volume": "60880842"}, "2022-01-19": {"1. open": "0.0070", "2. high": "0.0071", "3. low": "0.0056", "4. close": "0.0068", "5. volume": "62842878"}, "2022-01-18": {"1. open": "0.0075", "2. high": "0.0075", "3. low": "0.0067", "4. close": "0.0068", "5. volume": "62842878"}, "2022-01-14": {"1. open": "0.0070", "2. high": "0.0075", "3. low": "0.0067", "4. close": "0.0074", "5. volume": "44617269"}, "2022-01-13": {"1. open": "0.0079", "2. high": "0.0080", "3. low": "0.0070", "4. close": "0.0072", "5. volume": "64113367"}, "2022-01-12": {"1. open": "0.0078", "2. high": "0.0084", "3. low": "0.0075", "4. close": "0.0078", "5. volume": "67250272"}, "2022-01-11": {"1. open": "0.0090", "2. high": "0.0099", "3. low": "0.0074", "4. close": "0.0077", "5. volume": "289521455"}, "2022-01-10": {"1. open": "0.0079", "2. high": "0.0094", "3. low": "0.0071", "4. close": "0.0089", "5. volume": "177535726"}, "2022-01-07": {"1. open": "0.0080", "2. high": "0.0082", "3. low": "0.0064", "4. close": "0.0070", "5. volume": "164563559"}, "2022-01-06": {"1. open": "0.0082", "2. high": "0.0083", "3. low": "0.0076", "4. close": "0.0079", "5. volume": "50766922"}, "2022-01-05": {"1. open": "0.0085", "2. high": "0.0086", "3. low": "0.0080", "4. close": "0.0081", "5. volume": "62304395"}, "2022-01-04": {"1. open": "0.0089", "2. high": "0.0090", "3. low": "0.0075", "4. close": "0.0083", "5. volume": "120496782"}, "2022-01-03": {"1. open": "0.0095", "2. high": "0.0097", "3. low": "0.0087", "4. close": "0.0088", "5. volume": "77605081"}, "2021-12-31": {"1. open": "0.0084", "2. high": "0.0089", "3. low": "0.0072", "4. close": "0.0089", "5. volume": "94869969"}, "2021-12-30": {"1. open": "0.0077", "2. high": "0.0090", "3. low": "0.0076", "4. close": "0.0080", "5. volume": "112827746"}, "2021-12-29": {"1. open": "0.0084", "2. high": "0.0088", "3. low": "0.0076", "4. close": "0.0085", "5. volume": "87622488"}, "2021-12-28": {"1. open": "0.0096", "2. high": "0.0097", "3. low": "0.0080", "4. close": "0.0085", "5. volume": "93594996"}, "2021-12-27": {"1. open": "0.0092", "2. high": "0.0108", "3. low": "0.0091", "4. close": "0.0096", "5. volume": "131037986"}, "2021-12-23": {"1. open": "0.0081", "2. high": "0.0095", "3. low": "0.0070", "4. close": "0.0090", "5. volume": "232406466"}, "2021-12-22": {"1. open": "0.0090", "2. high": "0.0094", "3. low": "0.0071", "4. close": "0.0079", "5. volume": "334021755"}, "2021-12-21": {"1. open": "0.0108", "2. high": "0.0117", "3. low": "0.0085", "4. close": "0.0090", "5. volume": "383294135"}, "2021-12-20": {"1. open": "0.0146", "2. high": "0.0155", "3. low": "0.0104", "4. close": "0.0108", "5. volume": "640607105"}, "2021-12-17": {"1. open": "0.0113", "2. high": "0.0130", "3. low": "0.0105", "4. close": "0.0128", "5. volume": "171215347"}, "2021-12-16": {"1. open": "0.0123", "2. high": "0.0134", "3. low": "0.0105", "4. close": "0.0111", "5. volume": "201748133"}, "2021-12-15": {"1. open": "0.0109", "2. high": "0.0133", "3. low": "0.0105", "4. close": "0.0123", "5. volume": "373791246"}, "2021-12-14": {"1. open": "0.0080", "2. high": "0.0102", "3. low": "0.0073", "4. close": "0.0101", "5. volume": "370312914"}, "2021-12-13": {"1. open": "0.0062", "2. high": "0.0075", "3. low": "0.0055", "4. close": "0.0073", "5. volume": "324206305"}, "2021-12-10": {"1. open": "0.0058", "2. high": "0.0065", "3. low": "0.0058", "4. close": "0.0060", "5. volume": "191433772"}, "2021-12-09": {"1. open": "0.0063", "2. high": "0.0065", "3. low": "0.0057", "4. close": "0.0059", "5. volume": "204533064"}, "2021-12-08": {"1. open": "0.0060", "2. high": "0.0068", "3. low": "0.0057", "4. close": "0.0059", "5. volume": "357094245"}, "2021-12-07": {"1. open": "0.0054", "2. high": "0.0057", "3. low": "0.0049", "4. close": "0.0054", "5. volume": "151638840"}, "2021-12-06": {"1. open": "0.0055", "2. high": "0.0057", "3. low": "0.0049", "4. close": "0.0051", "5. volume": "95273752"}, "2021-12-03": {"1. open": "0.0051", "2. high": "0.0061", "3. low": "0.0047", "4. close": "0.0049", "5. volume": "134336086"}, "2021-12-02": {"1. open": "0.0070", "2. high": "0.0074", "3. low": "0.0046", "4. close": "0.0052", "5. volume": "385596951"}, "2021-12-01": {"1. open": "0.0083", "2. high": "0.0085", "3. low": "0.0062", "4. close": "0.0065", "5. volume": "228720444"}, "2021-11-30": {"1. open": "0.0095", "2. high": "0.0095", "3. low": "0.0076", "4. close": "0.0079", "5. volume": "100180894"}, "2021-11-29": {"1. open": "0.0100", "2. high": "0.0104", "3. low": "0.0085", "4. close": "0.0087", "5. volume": "48816253"}, "2021-11-26": {"1. open": "0.0096", "2. high": "0.0109", "3. low": "0.0095", "4. close": "0.0103", "5. volume": "29688409"}, "2021-11-24": {"1. open": "0.0128", "2. high": "0.0130", "3. low": "0.0100", "4. close": "0.0108", "5. volume": "72874846"}, "2021-11-23": {"1. open": "0.0087", "2. high": "0.0096", "3. low": "0.0080", "4. close": "0.0096", "5. volume": "40918882"}, "2021-11-22": {"1. open": "0.0105", "2. high": "0.0105", "3. low": "0.0079", "4. close": "0.0087", "5. volume": "66513283"}, "2021-11-19": {"1. open": "0.0120", "2. high": "0.0128", "3. low": "0.0099", "4. close": "0.0105", "5. volume": "44678500"}, "2021-11-18": {"1. open": "0.0125", "2. high": "0.0138", "3. low": "0.0111", "4. close": "0.0116", "5. volume": "33470287"}, "2021-11-17": {"1. open": "0.0124", "2. high": "0.0132", "3. low": "0.0111", "4. close": "0.0123", "5. volume": "19689563"}, "2021-11-16": {"1. open": "0.0138", "2. high": "0.0144", "3. low": "0.0101", "4. close": "0.0123", "5. volume": "76240293"}, "2021-11-15": {"1. open": "0.0138", "2. high": "0.0155", "3. low": "0.0131", "4. close": "0.0136", "5. volume": "22960192"}, "2021-11-12": {"1. open": "0.0126", "2. high": "0.0138", "3. low": "0.0114", "4. close": "0.0135", "5. volume": "24929241"}, "2021-11-11": {"1. open": "0.0145", "2. high": "0.0145", "3. low": "0.0115", "4. close": "0.0134", "5. volume": "36410120"}, "2021-11-10": {"1. open": "0.0141", "2. high": "0.0163", "3. low": "0.0130", "4. close": "0.0139", "5. volume": "34042954"}, "2021-11-09": {"1. open": "0.0137", "2. high": "0.0161", "3. low": "0.0133", "4. close": "0.0140", "5. volume": "41939353"}, "2021-11-08": {"1. open": "0.0130", "2. high": "0.0142", "3. low": "0.0128", "4. close": "0.0139", "5. volume": "18922688"}, "2021-11-05": {"1. open": "0.0114", "2. high": "0.0135", "3. low": "0.0110", "4. close": "0.0128", "5. volume": "34470215"}, "2021-11-04": {"1. open": "0.0108", "2. high": "0.0119", "3. low": "0.0105", "4. close": "0.0109", "5. volume": "23783511"}, "2021-11-03": {"1. open": "0.0116", "2. high": "0.0122", "3. low": "0.0097", "4. close": "0.0107", "5. volume": "44608808"}, "2021-11-02": {"1. open": "0.0115", "2. high": "0.0127", "3. low": "0.0093", "4. close": "0.0120", "5. volume": "56656726"}, "2021-11-01": {"1. open": "0.0145", "2. high": "0.0152", "3. low": "0.0115", "4. close": "0.0140", "5. volume": "72560654"}, "2021-10-29": {"1. open": "0.0147", "2. high": "0.0166", "3. low": "0.0127", "4. close": "0.0140", "5. volume": "72560654"}, "2021-10-28": {"1. open": "0.0198", "2. high": "0.0198", "3. low": "0.0140", "4. close": "0.0149", "5. volume": "78389564"}, "2021-10-27": {"1. open": "0.0195", "2. high": "0.0214", "3. low": "0.0190", "4. close": "0.0198", "5. volume": "111859768"}, "2021-10-26": {"1. open": "0.0200", "2. high": "0.0220", "3. low": "0.0182", "4. close": "0.0195", "5. volume": "167259770"}, "2021-10-25": {"1. open": "0.0193", "2. high": "0.0200", "3. low": "0.0165", "4. close": "0.0199", "5. volume": "62608134"}, "2021-10-22": {"1. open": "0.0172", "2. high": "0.0200", "3. low": "0.0151", "4. close": "0.0192", "5. volume": "98991655"}, "2021-10-21": {"1. open": "0.0180", "2. high": "0.0185", "3. low": "0.0164", "4. close": "0.0174", "5. volume": "38257695"}, "2021-10-20": {"1. open": "0.0187", "2. high": "0.0188", "3. low": "0.0163", "4. close": "0.0182", "5. volume": "39611442"}, "2021-10-19": {"1. open": "0.0187", "2. high": "0.0200", "3. low": "0.0165", "4. close": "0.0172", "5. volume": "29269700"}, "2021-10-18": {"1. open": "0.0170", "2. high": "0.0190", "3. low": "0.0152", "4. close": "0.0188", "5. volume": "82392201"}, "2021-10-15": {"1. open": "0.0191", "2. high": "0.0195", "3. low": "0.0161", "4. close": "0.0170", "5. volume": "62115106"}, "2021-10-14": {"1. open": "0.0215", "2. high": "0.0215", "3. low": "0.0175", "4. close": "0.0197", "5. volume": "79758636"}, "2021-10-13": {"1. open": "0.0236", "2. high": "0.0244", "3. low": "0.0195", "4. close": "0.0212", "5. volume": "108483367"}, "2021-10-12": {"1. open": "0.0217", "2. high": "0.0231", "3. low": "0.0204", "4. close": "0.0224", "5. volume": "42820268"}, "2021-10-11": {"1. open": "0.0196", "2. high": "0.0222", "3. low": "0.0195", "4. close": "0.0216", "5. volume": "41894854"}, "2021-10-08": {"1. open": "0.0205", "2. high": "0.0219", "3. low": "0.0186", "4. close": "0.0195", "5. volume": "123290822"}, "2021-10-07": {"1. open": "0.0191", "2. high": "0.0211", "3. low": "0.0170", "4. close": "0.0200", "5. volume": "80480563"}, "2021-10-06": {"1. open": "0.0200", "2. high": "0.0204", "3. low": "0.0177", "4. close": "0.0183", "5. volume": "50320521"}, "2021-10-05": {"1. open": "0.0199", "2. high": "0.0199", "3. low": "0.0169", "4. close": "0.0197", "5. volume": "44746090"}, "2021-10-04": {"1. open": "0.0199", "2. high": "0.0209", "3. low": "0.0152", "4. close": "0.0199", "5. volume": "148346719"}, "2021-10-01": {"1. open": "0.0257", "2. high": "0.0279", "3. low": "0.0190", "4. close": "0.0195", "5. volume": "334646341"}, "2021-09-30": {"1. open": "0.0170", "2. high": "0.0271", "3. low": "0.0166", "4. close": "0.0260", "5. volume": "252940828"}, "2021-09-29": {"1. open": "0.0160", "2. high": "0.0179", "3. low": "0.0145", "4. close": "0.0162", "5. volume": "49871628"}, "2021-09-28": {"1. open": "0.0151", "2. high": "0.0174", "3. low": "0.0151", "4. close": "0.0164", "5. volume": "37162411"}, "2021-09-27": {"1. open": "0.0170", "2. high": "0.0172", "3. low": "0.0145", "4. close": "0.0172", "5. volume": "46041726"}, "2021-09-24": {"1. open": "0.0136", "2. high": "0.0174", "3. low": "0.0121", "4. close": "0.0167", "5. volume": "105211631"}, "2021-09-23": {"1. open": "0.0174", "2. high": "0.0174", "3. low": "0.0136", "4. close": "0.0137", "5. volume": "91963067"}, "2021-09-22": {"1. open": "0.0181", "2. high": "0.0191", "3. low": "0.0152", "4. close": "0.0171", "5. volume": "116021375"}, "2021-09-21": {"1. open": "0.0132", "2. high": "0.0188", "3. low": "0.0132", "4. close": "0.0181", "5. volume": "159242992"}, "2021-09-20": {"1. open": "0.0112", "2. high": "0.0148", "3. low": "0.0096", "4. close": "0.0140", "5. volume": "188596523"}, "2021-09-17": {"1. open": "0.0094", "2. high": "0.0100", "3. low": "0.0080", "4. close": "0.0100", "5. volume": "100846989"}, "2021-09-16": {"1. open": "0.0067", "2. high": "0.0090", "3. low": "0.0062", "4. close": "0.0090", "5. volume": "154973569"}, "2021-09-15": {"1. open": "0.0063", "2. high": "0.0076", "3. low": "0.0063", "4. close": "0.0069", "5. volume": "185048531"}, "2021-09-14": {"1. open": "0.0043", "2. high": "0.0064", "3. low": "0.0043", "4. close": "0.0062", "5. volume": "102325665"}, "2021-09-13": {"1. open": "0.0039", "2. high": "0.0042", "3. low": "0.0036", "4. close": "0.0039", "5. volume": "9950993"}, "2021-09-10": {"1. open": "0.0036", "2. high": "0.0040", "3. low": "0.0036", "4. close": "0.0039", "5. volume": "10835259"}, "2021-09-09": {"1. open": "0.0044", "2. high": "0.0044", "3. low": "0.0035", "4. close": "0.0036", "5. volume": "10079971"}, "2021-09-08": {"1. open": "0.0039", "2. high": "0.0048", "3. low": "0.0036", "4. close": "0.0038", "5. volume": "11852949"}, "2021-09-07": {"1. open": "0.0050", "2. high": "0.0051", "3. low": "0.0022", "4. close": "0.0038", "5. volume": "41738512"}, "2021-09-03": {"1. open": "0.0037", "2. high": "0.0052", "3. low": "0.0031", "4. close": "0.0052", "5. volume": "103244077"}, "2021-09-02": {"1. open": "0.0042", "2. high": "0.0045", "3. low": "0.0038", "4. close": "0.0040", "5. volume": "34423491"}, "2021-09-01": {"1. open": "0.0050", "2. high": "0.0060", "3. low": "0.0040", "4. close": "0.0042", "5. volume": "72549527"}, "2021-08-31": {"1. open": "0.0044", "2. high": "0.0060", "3. low": "0.0040", "4. close": "0.0049", "5. volume": "102594605"}, "2021-08-30": {"1. open": "0.0044", "2. high": "0.0048", "3. low": "0.0041", "4. close": "0.0044", "5. volume": "65795186"}, "2021-08-27": {"1. open": "0.0038", "2. high": "0.0047", "3. low": "0.0037", "4. close": "0.0043", "5. volume": "136495105"}, "2021-08-26": {"1. open": "0.0032", "2. high": "0.0044", "3. low": "0.0024", "4. close": "0.0037", "5. volume": "177928456"}, "2021-08-25": {"1. open": "0.0031", "2. high": "0.0036", "3. low": "0.0029", "4. close": "0.0030", "5. volume": "73855602"}, "2021-08-24": {"1. open": "0.0031", "2. high": "0.0035", "3. low": "0.0029", "4. close": "0.0032", "5. volume": "88531301"}, "2021-08-23": {"1. open": "0.0020", "2. high": "0.0031", "3. low": "0.0020", "4. close": "0.0029", "5. volume": "172006203"}, "2021-08-20": {"1. open": "0.0025", "2. high": "0.0026", "3. low": "0.0021", "4. close": "0.0021", "5. volume": "71128887"}, "2021-08-19": {"1. open": "0.0025", "2. high": "0.0034", "3. low": "0.0023", "4. close": "0.0025", "5. volume": "111114273"}, "2021-08-18": {"1. open": "0.0031", "2. high": "0.0031", "3. low": "0.0022", "4. close": "0.0027", "5. volume": "190064421"}, "2021-08-17": {"1. open": "0.0021", "2. high": "0.0040", "3. low": "0.0021", "4. close": "0.0031", "5. volume": "751723140"}, "2021-08-16": {"1. open": "0.0014", "2. high": "0.0023", "3. low": "0.0014", "4. close": "0.0021", "5. volume": "109927555"}, "2021-08-13": {"1. open": "0.0014", "2. high": "0.0016", "3. low": "0.0014", "4. close": "0.0014", "5. volume": "24971426"}, "2021-08-12": {"1. open": "0.0014", "2. high": "0.0014", "3. low": "0.0013", "4. close": "0.0013", "5. volume": "10287355"}, "2021-08-11": {"1. open": "0.0014", "2. high": "0.0014", "3. low": "0.0012", "4. close": "0.0014", "5. volume": "47763454"}, "2021-08-10": {"1. open": "0.0015", "2. high": "0.0016", "3. low": "0.0014", "4. close": "0.0014", "5. volume": "32321924"}, "2021-08-09": {"1. open": "0.0019", "2. high": "0.0019", "3. low": "0.0014", "4. close": "0.0016", "5. volume": "68861807"}, "2021-08-06": {"1. open": "0.0017", "2. high": "0.0020", "3. low": "0.0016", "4. close": "0.0018", "5. volume": "85528433"}, "2021-08-05": {"1. open": "0.0013", "2. high": "0.0024", "3. low": "0.0012", "4. close": "0.0018", "5. volume": "501312521"}, "2021-08-04": {"1. open": "0.0012", "2. high": "0.0014", "3. low": "0.0011", "4. close": "0.0012", "5. volume": "27228757"}, "2021-08-03": {"1. open": "0.0012", "2. high": "0.0013", "3. low": "0.0010", "4. close": "0.0011", "5. volume": "14147589"}, "2021-08-02": {"1. open": "0.0012", "2. high": "0.0014", "3. low": "0.0012", "4. close": "0.0012", "5. volume": "56806627"}, "2021-07-30": {"1. open": "0.0007", "2. high": "0.0014", "3. low": "0.0007", "4. close": "0.0012", "5. volume": "99727585"}, "2021-07-29": {"1. open": "0.0008", "2. high": "0.0009", "3. low": "0.0007", "4. close": "0.0007", "5. volume": "10995540"}, "2021-07-28": {"1. open": "0.0008", "2. high": "0.0008", "3. low": "0.0007", "4. close": "0.0007", "5. volume": "7004008"}, "2021-07-27": {"1. open": "0.0008", "2. high": "0.0009", "3. low": "0.0007", "4. close": "0.0008", "5. volume": "9434966"}, "2021-07-26": {"1. open": "0.0009", "2. high": "0.0009", "3. low": "0.0007", "4. close": "0.0008", "5. volume": "8703592"}, "2021-07-23": {"1. open": "0.0009", "2. high": "0.0010", "3. low": "0.0008", "4. close": "0.0009", "5. volume": "19185637"}, "2021-07-22": {"1. open": "0.0010", "2. high": "0.0010", "3. low": "0.0009", "4. close": "0.0009", "5. volume": "13964164"}, "2021-07-21": {"1. open": "0.0006", "2. high": "0.0010", "3. low": "0.0005", "4. close": "0.0009", "5. volume": "136662533"}, "2021-07-20": {"1. open": "0.0006", "2. high": "0.0006", "3. low": "0.0005", "4. close": "0.0006", "5. volume": "15211658"}, "2021-07-19": {"1. open": "0.0006", "2. high": "0.0007", "3. low": "0.0006", "4. close": "0.0006", "5. volume": "16847320"}, "2021-07-16": {"1. open": "0.0007", "2. high": "0.0008", "3. low": "0.0005", "4. close": "0.0006", "5. volume": "51090950"}, "2021-07-15": {"1. open": "0.0006", "2. high": "0.0008", "3. low": "0.0006", "4. close": "0.0007", "5. volume": "31380367"}, "2021-07-14": {"1. open": "0.0007", "2. high": "0.0008", "3. low": "0.0006", "4. close": "0.0007", "5. volume": "51437693"}, "2021-07-13": {"1. open": "0.0008", "2. high": "0.0009", "3. low": "0.0006", "4. close": "0.0007", "5. volume": "108174101"}, "2021-07-12": {"1. open": "0.0008", "2. high": "0.0009", "3. low": "0.0008", "4. close": "0.0009", "5. volume": "14093441"}, "2021-07-09": {"1. open": "0.0009", "2. high": "0.0009", "3. low": "0.0008", "4. close": "0.0008", "5. volume": "6003590"}, "2021-07-08": {"1. open": "0.0010", "2. high": "0.0010", "3. low": "0.0008", "4. close": "0.0009", "5. volume": "9310793"}, "2021-07-07": {"1. open": "0.0009", "2. high": "0.0011", "3. low": "0.0008", "4. close": "0.0009", "5. volume": "41008786"}, "2021-07-06": {"1. open": "0.0010", "2. high": "0.0010", "3. low": "0.0009", "4. close": "0.0009", "5. volume": "11626517"}, "2021-07-02": {"1. open": "0.0010", "2. high": "0.0011", "3. low": "0.0010", "4. close": "0.0010", "5. volume": "16920425"}, "2021-07-01": {"1. open": "0.0009", "2. high": "0.0011", "3. low": "0.0009", "4. close": "0.0010", "5. volume": "15723116"}, "2021-06-30": {"1. open": "0.0010", "2. high": "0.0010", "3. low": "0.0009", "4. close": "0.0010", "5. volume": "16115347"}, "2021-06-29": {"1. open": "0.0007", "2. high": "0.0010", "3. low": "0.0007", "4. close": "0.0010", "5. volume": "60774031"}, "2021-06-28": {"1. open": "0.0008", "2. high": "0.0010", "3. low": "0.0007", "4. close": "0.0008", "5. volume": "92053237"}, "2021-06-25": {"1. open": "0.0011", "2. high": "0.0013", "3. low": "0.0008", "4. close": "0.0009", "5. volume": "214524663"}, "2021-06-24": {"1. open": "0.0022", "2. high": "0.0023", "3. low": "0.0012", "4. close": "0.0012", "5. volume": "273865287"}, "2021-06-23": {"1. open": "0.0024", "2. high": "0.0025", "3. low": "0.0019", "4. close": "0.0023", "5. volume": "109854555"}, "2021-06-22": {"1. open": "0.0025", "2. high": "0.0027", "3. low": "0.0019", "4. close": "0.0024", "5. volume": "106889486"}, "2021-06-21": {"1. open": "0.0022", "2. high": "0.0027", "3. low": "0.0020", "4. close": "0.0025", "5. volume": "212971639"}, "2021-06-18": {"1. open": "0.0016", "2. high": "0.0021", "3. low": "0.0014", "4. close": "0.0020", "5. volume": "188295196"}, "2021-06-17": {"1. open": "0.0012", "2. high": "0.0015", "3. low": "0.0012", "4. close": "0.0015", "5. volume": "85065005"}, "2021-06-16": {"1. open": "0.0013", "2. high": "0.0013", "3. low": "0.0012", "4. close": "0.0013", "5. volume": "42940940"}, "2021-06-15": {"1. open": "0.0014", "2. high": "0.0015", "3. low": "0.0012", "4. close": "0.0013", "5. volume": "87204142"}, "2021-06-14": {"1. open": "0.0013", "2. high": "0.0013", "3. low": "0.0011", "4. close": "0.0013", "5. volume": "92861108"}, "2021-06-11": {"1. open": "0.0013", "2. high": "0.0014", "3. low": "0.0012", "4. close": "0.0013", "5. volume": "58694263"}, "2021-06-10": {"1. open": "0.0013", "2. high": "0.0013", "3. low": "0.0012", "4. close": "0.0013", "5. volume": "48987057"}, "2021-06-09": {"1. open": "0.0014", "2. high": "0.0015", "3. low": "0.0012", "4. close": "0.0013", "5. volume": "108243108"}, "2021-06-08": {"1. open": "0.0015", "2. high": "0.0016", "3. low": "0.0012", "4. close": "0.0014", "5. volume": "168395203"}, "2021-06-07": {"1. open": "0.0011", "2. high": "0.0018", "3. low": "0.0010", "4. close": "0.0013", "5. volume": "493500646"}, "2021-06-04": {"1. open": "0.0008", "2. high": "0.0013", "3. low": "0.0008", "4. close": "0.0012", "5. volume": "379540972"}, "2021-06-03": {"1. open": "0.0009", "2. high": "0.0009", "3. low": "0.0008", "4. close": "0.0008", "5. volume": "140759315"}, "2021-06-02": {"1. open": "0.0010", "2. high": "0.0014", "3. low": "0.0008", "4. close": "0.0008", "5. volume": "1197849574"}, "2021-06-01": {"1. open": "0.0006", "2. high": "0.0008", "3. low": "0.0005", "4. close": "0.0007", "5. volume": "133507404"}, "2021-05-28": {"1. open": "0.0005", "2. high": "0.0006", "3. low": "0.0005", "4. close": "0.0006", "5. volume": "15589971"}, "2021-05-27": {"1. open": "0.0007", "2. high": "0.0007", "3. low": "0.0005", "4. close": "0.0006", "5. volume": "14339238"}, "2021-05-26": {"1. open": "0.0007", "2. high": "0.0007", "3. low": "0.0006", "4. close": "0.0006", "5. volume": "30861299"}, "2021-05-25": {"1. open": "0.0005", "2. high": "0.0007", "3. low": "0.0005", "4. close": "0.0007", "5. volume": "124572129"}, "2021-05-24": {"1. open": "0.0005", "2. high": "0.0006", "3. low": "0.0004", "4. close": "0.0005", "5. volume": "57879940"}, "2021-05-21": {"1. open": "0.0004", "2. high": "0.0005", "3. low": "0.0004", "4. close": "0.0005", "5. volume": "28013055"}, "2021-05-20": {"1. open": "0.0005", "2. high": "0.0005", "3. low": "0.0004", "4. close": "0.0004", "5. volume": "22045000"}, "2021-05-19": {"1. open": "0.0005", "2. high": "0.0005", "3. low": "0.0004", "4. close": "0.0005", "5. volume": "66453614"}, "2021-05-18": {"1. open": "0.0004", "2. high": "0.0005", "3. low": "0.0004", "4. close": "0.0005", "5. volume": "21057850"}, "2021-05-17": {"1. open": "0.0004", "2. high": "0.0005", "3. low": "0.0004", "4. close": "0.0005", "5. volume": "26851132"}, "2021-05-14": {"1. open": "0.0005", "2. high": "0.0005", "3. low": "0.0004", "4. close": "0.0005", "5. volume": "5583019"}, "2021-05-13": {"1. open": "0.0004", "2. high": "0.0005", "3. low": "0.0004", "4. close": "0.0005", "5. volume": "4282500"}, "2021-05-12": {"1. open": "0.0004", "2. high": "0.0005", "3. low": "0.0004", "4. close": "0.0004", "5. volume": "7934499"}, "2021-05-11": {"1. open": "0.0005", "2. high": "0.0006", "3. low": "0.0004", "4. close": "0.0004", "5. volume": "17666177"}, "2021-05-10": {"1. open": "0.0005", "2. high": "0.0006", "3. low": "0.0004", "4. close": "0.0005", "5. volume": "45615500"}, "2021-05-07": {"1. open": "0.0006", "2. high": "0.0006", "3. low": "0.0005", "4. close": "0.0005", "5. volume": "121885000"}, "2021-05-06": {"1. open": "0.0005", "2. high": "0.0006", "3. low": "0.0004", "4. close": "0.0005", "5. volume": "326120341"}, "2021-05-05": {"1. open": "0.0005", "2. high": "0.0005", "3. low": "0.0004", "4. close": "0.0004", "5. volume": "101098001"}, "2021-05-04": {"1. open": "0.0006", "2. high": "0.0006", "3. low": "0.0004", "4. close": "0.0004", "5. volume": "7616651"}, "2021-05-03": {"1. open": "0.0006", "2. high": "0.0006", "3. low": "0.0004", "4. close": "0.0006", "5. volume": "75339106"}, "2021-04-30": {"1. open": "0.0005", "2. high": "0.0006", "3. low": "0.0005", "4. close": "0.0006", "5. volume": "12436665"}, "2021-04-29": {"1. open": "0.0006", "2. high": "0.0007", "3. low": "0.0005", "4. close": "0.0005", "5. volume": "44252897"}, "2021-04-28": {"1. open": "0.0006", "2. high": "0.0006", "3. low": "0.0005", "4. close": "0.0006", "5. volume": "41422690"}, "2021-04-27": {"1. open": "0.0005", "2. high": "0.0007", "3. low": "0.0004", "4. close": "0.0006", "5. volume": "312526796"}, "2021-04-26": {"1. open": "0.0005", "2. high": "0.0005", "3. low": "0.0004", "4. close": "0.0004", "5. volume": "14271426"}, "2021-04-23": {"1. open": "0.0004", "2. high": "0.0005", "3. low": "0.0004", "4. close": "0.0005", "5. volume": "14897799"}, "2021-04-22": {"1. open": "0.0004", "2. high": "0.0005", "3. low": "0.0004", "4. close": "0.0004", "5. volume": "11483282"}, "2021-04-21": {"1. open": "0.0005", "2. high": "0.0006", "3. low": "0.0004", "4. close": "0.0004", "5. volume": "40518544"}, "2021-04-20": {"1. open": "0.0005", "2. high": "0.0006", "3. low": "0.0004", "4. close": "0.0005", "5. volume": "59512082"}, "2021-04-19": {"1. open": "0.0004", "2. high": "0.0007", "3. low": "0.0004", "4. close": "0.0005", "5. volume": "464857934"}, "2021-04-16": {"1. open": "0.0003", "2. high": "0.0004", "3. low": "0.0003", "4. close": "0.0003", "5. volume": "13615555"}, "2021-04-15": {"1. open": "0.0004", "2. high": "0.0004", "3. low": "0.0003", "4. close": "0.0004", "5. volume": "8150789"}, "2021-04-14": {"1. open": "0.0004", "2. high": "0.0004", "3. low": "0.0003", "4. close": "0.0004", "5. volume": "2439500"}, "2021-04-13": {"1. open": "0.0004", "2. high": "0.0004", "3. low": "0.0003", "4. close": "0.0003", "5. volume": "8552500"}, "2021-04-12": {"1. open": "0.0004", "2. high": "0.0004", "3. low": "0.0003", "4. close": "0.0003", "5. volume": "17631184"}, "2021-04-09": {"1. open": "0.0004", "2. high": "0.0004", "3. low": "0.0003", "4. close": "0.0003", "5. volume": "6432001"}, "2021-04-08": {"1. open": "0.0004", "2. high": "0.0004", "3. low": "0.0003", "4. close": "0.0003", "5. volume": "13795901"}, "2021-04-07": {"1. open": "0.0004", "2. high": "0.0004", "3. low": "0.0003", "4. close": "0.0003", "5. volume": "25320001"}, "2021-04-06": {"1. open": "0.0004", "2. high": "0.0004", "3. low": "0.0003", "4. close": "0.0004", "5. volume": "29873030"}, "2021-04-05": {"1. open": "0.0004", "2. high": "0.0004", "3. low": "0.0003", "4. close": "0.0003", "5. volume": "17848657"}, "2021-04-01": {"1. open": "0.0004", "2. high": "0.0004", "3. low": "0.0003", "4. close": "0.0003", "5. volume": "12822427"}, "2021-03-31": {"1. open": "0.0004", "2. high": "0.0004", "3. low": "0.0003", "4. close": "0.0004", "5. volume": "13520025"}, "2021-03-30": {"1. open": "0.0002", "2. high": "0.0004", "3. low": "0.0002", "4. close": "0.0004", "5. volume": "86548107"}, "2021-03-29": {"1. open": "0.0004", "2. high": "0.0004", "3. low": "0.0002", "4. close": "0.0002", "5. volume": "38600415"}, "2021-03-26": {"1. open": "0.0004", "2. high": "0.0004", "3. low": "0.0003", "4. close": "0.0003", "5. volume": "85840989"}, "2021-03-25": {"1. open": "0.0004", "2. high": "0.0004", "3. low": "0.0003", "4. close": "0.0003", "5. volume": "17543998"}, "2021-03-24": {"1. open": "0.0004", "2. high": "0.0004", "3. low": "0.0003", "4. close": "0.0004", "5. volume": "14250300"}, "2021-03-23": {"1. open": "0.0004", "2. high": "0.0004", "3. low": "0.0003", "4. close": "0.0004", "5. volume": "13977599"}, "2021-03-22": {"1. open": "0.0004", "2. high": "0.0004", "3. low": "0.0003", "4. close": "0.0004", "5. volume": "5925276"}, "2021-03-19": {"1. open": "0.0004", "2. high": "0.0004", "3. low": "0.0003", "4. close": "0.0003", "5. volume": "23237600"}, "2021-03-18": {"1. open": "0.0004", "2. high": "0.0004", "3. low": "0.0003", "4. close": "0.0004", "5. volume": "5615413"}, "2021-03-17": {"1. open": "0.0004", "2. high": "0.0004", "3. low": "0.0003", "4. close": "0.0004", "5. volume": "12010118"}, "2021-03-16": {"1. open": "0.0003", "2. high": "0.0004", "3. low": "0.0003", "4. close": "0.0004", "5. volume": "28102298"}, "2021-03-15": {"1. open": "0.0004", "2. high": "0.0004", "3. low": "0.0003", "4. close": "0.0004", "5. volume": "13651974"}, "2021-03-12": {"1. open": "0.0004", "2. high": "0.0004", "3. low": "0.0003", "4. close": "0.0004", "5. volume": "476000"}, "2021-03-11": {"1. open": "0.0004", "2. high": "0.0005", "3. low": "0.0003", "4. close": "0.0004", "5. volume": "23616219"}, "2021-03-10": {"1. open": "0.0005", "2. high": "0.0005", "3. low": "0.0004", "4. close": "0.0004", "5. volume": "7916572"}, "2021-03-09": {"1. open": "0.0004", "2. high": "0.0005", "3. low": "0.0003", "4. close": "0.0005", "5. volume": "26114108"}, "2021-03-08": {"1. open": "0.0004", "2. high": "0.0004", "3. low": "0.0003", "4. close": "0.0004", "5. volume": "24434698"}, "2021-03-05": {"1. open": "0.0003", "2. high": "0.0004", "3. low": "0.0003", "4. close": "0.0004", "5. volume": "26020029"}, "2021-03-04": {"1. open": "0.0004", "2. high": "0.0004", "3. low": "0.0003", "4. close": "0.0004", "5. volume": "50669467"}, "2021-03-03": {"1. open": "0.0005", "2. high": "0.0005", "3. low": "0.0003", "4. close": "0.0004", "5. volume": "37609980"}, "2021-03-02": {"1. open": "0.0005", "2. high": "0.0005", "3. low": "0.0003", "4. close": "0.0005", "5. volume": "46143871"}, "2021-03-01": {"1. open": "0.0004", "2. high": "0.0006", "3. low": "0.0003", "4. close": "0.0005", "5. volume": "244139710"}, "2021-02-26": {"1. open": "0.0007", "2. high": "0.0007", "3. low": "0.0004", "4. close": "0.0006", "5. volume": "62454860"}, "2021-02-25": {"1. open": "0.0007", "2. high": "0.0007", "3. low": "0.0006", "4. close": "0.0006", "5. volume": "164964664"}, "2021-02-24": {"1. open": "0.0006", "2. high": "0.0008", "3. low": "0.0005", "4. close": "0.0006", "5. volume": "164964664"}, "2021-02-23": {"1. open": "0.0006", "2. high": "0.0006", "3. low": "0.0004", "4. close": "0.0005", "5. volume": "57267368"}, "2021-02-22": {"1. open": "0.0006", "2. high": "0.0007", "3. low": "0.0004", "4. close": "0.0005", "5. volume": "124622959"}, "2021-02-19": {"1. open": "0.0009", "2. high": "0.0009", "3. low": "0.0005", "4. close": "0.0006", "5. volume": "254386901"}, "2021-02-18": {"1. open": "0.0009", "2. high": "0.0009", "3. low": "0.0007", "4. close": "0.0008", "5. volume": "282406345"}, "2021-02-17": {"1. open": "0.0007", "2. high": "0.0010", "3. low": "0.0007", "4. close": "0.0008", "5. volume": "282406345"}, "2021-02-16": {"1. open": "0.0008", "2. high": "0.0009", "3. low": "0.0007", "4. close": "0.0008", "5. volume": "93951060"}, "2021-02-12": {"1. open": "0.0010", "2. high": "0.0010", "3. low": "0.0006", "4. close": "0.0008", "5. volume": "326411303"}, "2021-02-11": {"1. open": "0.0010", "2. high": "0.0011", "3. low": "0.0009", "4. close": "0.0010", "5. volume": "100736540"}, "2021-02-10": {"1. open": "0.0009", "2. high": "0.0012", "3. low": "0.0008", "4. close": "0.0010", "5. volume": "220363001"}, "2021-02-09": {"1. open": "0.0008", "2. high": "0.0011", "3. low": "0.0007", "4. close": "0.0010", "5. volume": "220363001"}, "2021-02-08": {"1. open": "0.0004", "2. high": "0.0007", "3. low": "0.0004", "4. close": "0.0007", "5. volume": "197461178"}, "2021-02-05": {"1. open": "0.0004", "2. high": "0.0006", "3. low": "0.0004", "4. close": "0.0005", "5. volume": "358816404"}, "2021-02-04": {"1. open": "0.0004", "2. high": "0.0005", "3. low": "0.0003", "4. close": "0.0004", "5. volume": "264870927"}, "2021-02-03": {"1. open": "0.0003", "2. high": "0.0004", "3. low": "0.0003", "4. close": "0.0003", "5. volume": "15044811"}, "2021-02-02": {"1. open": "0.0004", "2. high": "0.0004", "3. low": "0.0003", "4. close": "0.0003", "5. volume": "15149675"}, "2021-02-01": {"1. open": "0.0003", "2. high": "0.0004", "3. low": "0.0003", "4. close": "0.0003", "5. volume": "28211503"}, "2021-01-29": {"1. open": "0.0004", "2. high": "0.0004", "3. low": "0.0003", "4. close": "0.0003", "5. volume": "17661570"}, "2021-01-28": {"1. open": "0.0003", "2. high": "0.0004", "3. low": "0.0002", "4. close": "0.0004", "5. volume": "325061119"}, "2021-01-27": {"1. open": "0.0003", "2. high": "0.0005", "3. low": "0.0003", "4. close": "0.0003", "5. volume": "120231385"}, "2021-01-26": {"1. open": "0.0002", "2. high": "0.0005", "3. low": "0.0002", "4. close": "0.0004", "5. volume": "316697908"}, "2021-01-25": {"1. open": "0.0003", "2. high": "0.0003", "3. low": "0.0002", "4. close": "0.0002", "5. volume": "41387594"}, "2021-01-22": {"1. open": "0.0003", "2. high": "0.0003", "3. low": "0.0002", "4. close": "0.0003", "5. volume": "17715333"}, "2021-01-21": {"1. open": "0.0002", "2. high": "0.0003", "3. low": "0.0002", "4. close": "0.0003", "5. volume": "208080500"}, "2021-01-20": {"1. open": "0.0003", "2. high": "0.0003", "3. low": "0.0002", "4. close": "0.0002", "5. volume": "54552992"}, "2021-01-19": {"1. open": "0.0001", "2. high": "0.0004", "3. low": "0.0001", "4. close": "0.0003", "5. volume": "306239916"}, "2021-01-15": {"1. open": "0.0001", "2. high": "0.0001", "3. low": "0.0001", "4. close": "0.0001", "5. volume": "2000654"}, "2021-01-14": {"1. open": "0.0001", "2. high": "0.0002", "3. low": "0.0001", "4. close": "0.0001", "5. volume": "6180000"}, "2021-01-13": {"1. open": "0.0002", "2. high": "0.0002", "3. low": "0.0001", "4. close": "0.0001", "5. volume": "9834650"}, "2021-01-12": {"1. open": "0.0001", "2. high": "0.0002", "3. low": "0.0001", "4. close": "0.0001", "5. volume": "19360000"}, "2021-01-11": {"1. open": "0.0001", "2. high": "0.0001", "3. low": "0.0001", "4. close": "0.0001", "5. volume": "2000000"}, "2021-01-08": {"1. open": "0.0001", "2. high": "0.0001", "3. low": "0.0001", "4. close": "0.0001", "5. volume": "2150002"}, "2021-01-07": {"1. open": "0.0002", "2. high": "0.0002", "3. low": "0.0001", "4. close": "0.0001", "5. volume": "547275"}, "2021-01-06": {"1. open": "0.0001", "2. high": "0.0001", "3. low": "0.0001", "4. close": "0.0001", "5. volume": "15119999"}, "2021-01-05": {"1. open": "0.0001", "2. high": "0.0001", "3. low": "0.0001", "4. close": "0.0001", "5. volume": "13480000"}, "2021-01-04": {"1. open": "0.0001", "2. high": "0.0002", "3. low": "0.0001", "4. close": "0.0001", "5. volume": "4600101"}, "2020-12-31": {"1. open": "0.0002", "2. high": "0.0002", "3. low": "0.0001", "4. close": "0.0002", "5. volume": "63456052"}, "2020-12-30": {"1. open": "0.0001", "2. high": "0.0002", "3. low": "0.0001", "4. close": "0.0001", "5. volume": "4930039"}, "2020-12-29": {"1. open": "0.0001", "2. high": "0.0001", "3. low": "0.0001", "4. close": "0.0001", "5. volume": "2902115"}, "2020-12-28": {"1. open": "0.0001", "2. high": "0.0001", "3. low": "0.0001", "4. close": "0.0001", "5. volume": "4600070"}, "2020-12-24": {"1. open": "0.0001", "2. high": "0.0001", "3. low": "0.0001", "4. close": "0.0001", "5. volume": "2149812"}, "2020-12-23": {"1. open": "0.0001", "2. high": "0.0001", "3. low": "0.0001", "4. close": "0.0001", "5. volume": "30909113"}, "2020-12-22": {"1. open": "0.0001", "2. high": "0.0002", "3. low": "0.0001", "4. close": "0.0001", "5. volume": "15775851"}, "2020-12-21": {"1. open": "0.0001", "2. high": "0.0001", "3. low": "0.0001", "4. close": "0.0001", "5. volume": "9512184"}, "2020-12-18": {"1. open": "0.0001", "2. high": "0.0002", "3. low": "0.0001", "4. close": "0.0002", "5. volume": "25192500"}, "2020-12-17": {"1. open": "0.0001", "2. high": "0.0002", "3. low": "0.0001", "4. close": "0.0001", "5. volume": "13584800"}, "2020-12-16": {"1. open": "0.0001", "2. high": "0.0001", "3. low": "0.0001", "4. close": "0.0001", "5. volume": "6484000"}, "2020-12-15": {"1. open": "0.0001", "2. high": "0.0001", "3. low": "0.0001", "4. close": "0.0001", "5. volume": "22801000"}, "2020-12-14": {"1. open": "0.0001", "2. high": "0.0001", "3. low": "0.0001", "4. close": "0.0001", "5. volume": "16739998"}, "2020-12-11": {"1. open": "0.0001", "2. high": "0.0001", "3. low": "0.0001", "4. close": "0.0001", "5. volume": "1600000"}, "2020-12-10": {"1. open": "0.0001", "2. high": "0.0001", "3. low": "0.0001", "4. close": "0.0001", "5. volume": "28789995"}, "2020-12-09": {"1. open": "0.0001", "2. high": "0.0001", "3. low": "0.0001", "4. close": "0.0001", "5. volume": "28789995"}, "2020-12-08": {"1. open": "0.0003", "2. high": "0.0003", "3. low": "0.0001", "4. close": "0.0001", "5. volume": "409552827"}, "2020-12-07": {"1. open": "0.0001", "2. high": "0.0003", "3. low": "0.0001", "4. close": "0.0002", "5. volume": "1024146943"}, "2020-12-04": {"1. open": "0.0001", "2. high": "0.0001", "3. low": "0.0001", "4. close": "0.0001", "5. volume": "298962885"}, "2020-12-03": {"1. open": "0.0001", "2. high": "0.0001", "3. low": "0.0001", "4. close": "0.0001", "5. volume": "2959999"}, "2020-12-02": {"1. open": "0.0001", "2. high": "0.0001", "3. low": "0.0001", "4. close": "0.0001", "5. volume": "500000"}, "2020-12-01": {"1. open": "0.0001", "2. high": "0.0001", "3. low": "0.0001", "4. close": "0.0001", "5. volume": "602000"}, "2020-11-30": {"1. open": "0.0001", "2. high": "0.0001", "3. low": "0.0001", "4. close": "0.0001", "5. volume": "504000"}, "2020-11-27": {"1. open": "0.0001", "2. high": "0.0001", "3. low": "0.0001", "4. close": "0.0001", "5. volume": "3000"}, "2020-11-25": {"1. open": "0.0001", "2. high": "0.0001", "3. low": "0.0001", "4. close": "0.0001", "5. volume": "50"}, "2020-11-24": {"1. open": "0.0001", "2. high": "0.0001", "3. low": "0.0001", "4. close": "0.0001", "5. volume": "1"}, "2020-11-23": {"1. open": "0.0000", "2. high": "0.0000", "3. low": "0.0000", "4. close": "0.0000", "5. volume": "1399000"}, "2020-11-20": {"1. open": "0.0000", "2. high": "0.0000", "3. low": "0.0000", "4. close": "0.0000", "5. volume": "1399000"}, "2020-11-19": {"1. open": "0.0001", "2. high": "0.0001", "3. low": "0.0001", "4. close": "0.0001", "5. volume": "500000"}, "2020-11-18": {"1. open": "0.0001", "2. high": "0.0001", "3. low": "0.0001", "4. close": "0.0001", "5. volume": "0"}, "2020-11-17": {"1. open": "0.0001", "2. high": "0.0001", "3. low": "0.0001", "4. close": "0.0001", "5. volume": "0"}, "2020-11-16": {"1. open": "0.0001", "2. high": "0.0001", "3. low": "0.0001", "4. close": "0.0001", "5. volume": "1000999"}, "2020-11-13": {"1. open": "0.0001", "2. high": "0.0001", "3. low": "0.0001", "4. close": "0.0001", "5. volume": "1"}, "2020-11-12": {"1. open": "0.0001", "2. high": "0.0001", "3. low": "0.0001", "4. close": "0.0001", "5. volume": "0"}, "2020-11-11": {"1. open": "0.0001", "2. high": "0.0001", "3. low": "0.0001", "4. close": "0.0001", "5. volume": "0"}, "2020-11-10": {"1. open": "0.0001", "2. high": "0.0001", "3. low": "0.0001", "4. close": "0.0001", "5. volume": "1000"}, "2020-11-09": {"1. open": "0.0000", "2. high": "0.0000", "3. low": "0.0000", "4. close": "0.0000", "5. volume": "0"}, "2020-11-06": {"1. open": "0.0000", "2. high": "0.0000", "3. low": "0.0000", "4. close": "0.0000", "5. volume": "0"}, "2020-11-05": {"1. open": "0.0000", "2. high": "0.0000", "3. low": "0.0000", "4. close": "0.0000", "5. volume": "0"}, "2020-11-04": {"1. open": "0.0000", "2. high": "0.0000", "3. low": "0.0000", "4. close": "0.0000", "5. volume": "0"}, "2020-11-03": {"1. open": "0.0000", "2. high": "0.0000", "3. low": "0.0000", "4. close": "0.0000", "5. volume": "376"}, "2020-11-02": {"1. open": "0.0001", "2. high": "0.0001", "3. low": "0.0001", "4. close": "0.0001", "5. volume": "0"}, "2020-10-30": {"1. open": "0.0001", "2. high": "0.0001", "3. low": "0.0001", "4. close": "0.0001", "5. volume": "1000"}, "2020-10-29": {"1. open": "0.0001", "2. high": "0.0001", "3. low": "0.0001", "4. close": "0.0001", "5. volume": "166132"}, "2020-10-28": {"1. open": "0.0001", "2. high": "0.0001", "3. low": "0.0001", "4. close": "0.0001", "5. volume": "501000"}, "2020-10-27": {"1. open": "0.0000", "2. high": "0.0000", "3. low": "0.0000", "4. close": "0.0000", "5. volume": "0"}, "2020-10-26": {"1. open": "0.0000", "2. high": "0.0000", "3. low": "0.0000", "4. close": "0.0000", "5. volume": "0"}, "2020-10-23": {"1. open": "0.0000", "2. high": "0.0000", "3. low": "0.0000", "4. close": "0.0000", "5. volume": "0"}, "2020-10-22": {"1. open": "0.0000", "2. high": "0.0000", "3. low": "0.0000", "4. close": "0.0000", "5. volume": "1500004"}, "2020-10-21": {"1. open": "0.0001", "2. high": "0.0001", "3. low": "0.0001", "4. close": "0.0001", "5. volume": "0"}, "2020-10-20": {"1. open": "0.0001", "2. high": "0.0001", "3. low": "0.0001", "4. close": "0.0001", "5. volume": "0"}, "2020-10-19": {"1. open": "0.0001", "2. high": "0.0001", "3. low": "0.0001", "4. close": "0.0001", "5. volume": "0"}, "2020-10-16": {"1. open": "0.0001", "2. high": "0.0001", "3. low": "0.0001", "4. close": "0.0001", "5. volume": "0"}, "2020-10-15": {"1. open": "0.0001", "2. high": "0.0001", "3. low": "0.0001", "4. close": "0.0001", "5. volume": "0"}, "2020-10-14": {"1. open": "0.0001", "2. high": "0.0001", "3. low": "0.0001", "4. close": "0.0001", "5. volume": "0"}, "2020-10-13": {"1. open": "0.0001", "2. high": "0.0001", "3. low": "0.0001", "4. close": "0.0001", "5. volume": "0"}, "2020-10-12": {"1. open": "0.0001", "2. high": "0.0001", "3. low": "0.0001", "4. close": "0.0001", "5. volume": "0"}, "2020-10-09": {"1. open": "0.0001", "2. high": "0.0001", "3. low": "0.0001", "4. close": "0.0001", "5. volume": "0"}, "2020-10-08": {"1. open": "0.0001", "2. high": "0.0001", "3. low": "0.0001", "4. close": "0.0001", "5. volume": "300001"}, "2020-10-07": {"1. open": "0.0001", "2. high": "0.0001", "3. low": "0.0001", "4. close": "0.0001", "5. volume": "0"}, "2020-10-06": {"1. open": "0.0001", "2. high": "0.0001", "3. low": "0.0001", "4. close": "0.0001", "5. volume": "710000"}, "2020-10-05": {"1. open": "0.0001", "2. high": "0.0001", "3. low": "0.0001", "4. close": "0.0001", "5. volume": "0"}, "2020-10-02": {"1. open": "0.0001", "2. high": "0.0001", "3. low": "0.0001", "4. close": "0.0001", "5. volume": "0"}, "2020-10-01": {"1. open": "0.0001", "2. high": "0.0001", "3. low": "0.0001", "4. close": "0.0001", "5. volume": "100000"}, "2020-09-30": {"1. open": "0.0001", "2. high": "0.0001", "3. low": "0.0001", "4. close": "0.0001", "5. volume": "0"}, "2020-09-29": {"1. open": "0.0001", "2. high": "0.0001", "3. low": "0.0001", "4. close": "0.0001", "5. volume": "0"}, "2020-09-28": {"1. open": "0.0001", "2. high": "0.0001", "3. low": "0.0001", "4. close": "0.0001", "5. volume": "30000"}, "2020-09-25": {"1. open": "0.0001", "2. high": "0.0001", "3. low": "0.0001", "4. close": "0.0001", "5. volume": "10000"}, "2020-09-24": {"1. open": "0.0001", "2. high": "0.0001", "3. low": "0.0001", "4. close": "0.0001", "5. volume": "1"}, "2020-09-23": {"1. open": "0.0001", "2. high": "0.0001", "3. low": "0.0001", "4. close": "0.0001", "5. volume": "20000"}, "2020-09-22": {"1. open": "0.0001", "2. high": "0.0001", "3. low": "0.0001", "4. close": "0.0001", "5. volume": "0"}, "2020-09-21": {"1. open": "0.0001", "2. high": "0.0001", "3. low": "0.0001", "4. close": "0.0001", "5. volume": "0"}, "2020-09-18": {"1. open": "0.0001", "2. high": "0.0001", "3. low": "0.0001", "4. close": "0.0001", "5. volume": "10000"}, "2020-09-17": {"1. open": "0.0001", "2. high": "0.0001", "3. low": "0.0001", "4. close": "0.0001", "5. volume": "10000"}, "2020-09-16": {"1. open": "0.0001", "2. high": "0.0001", "3. low": "0.0001", "4. close": "0.0001", "5. volume": "60249"}, "2020-09-15": {"1. open": "0.0000", "2. high": "0.0000", "3. low": "0.0000", "4. close": "0.0000", "5. volume": "1000000"}, "2020-09-14": {"1. open": "0.0000", "2. high": "0.0000", "3. low": "0.0000", "4. close": "0.0000", "5. volume": "1000000"}, "2020-09-11": {"1. open": "0.0001", "2. high": "0.0001", "3. low": "0.0001", "4. close": "0.0001", "5. volume": "0"}, "2020-09-10": {"1. open": "0.0000", "2. high": "0.0000", "3. low": "0.0000", "4. close": "0.0000", "5. volume": "230000"}, "2020-09-09": {"1. open": "0.0001", "2. high": "0.0001", "3. low": "0.0000", "4. close": "0.0000", "5. volume": "230000"}, "2020-09-08": {"1. open": "0.0001", "2. high": "0.0001", "3. low": "0.0001", "4. close": "0.0001", "5. volume": "5000"}, "2020-09-04": {"1. open": "0.0001", "2. high": "0.0001", "3. low": "0.0001", "4. close": "0.0001", "5. volume": "11000"}, "2020-09-03": {"1. open": "0.0000", "2. high": "0.0000", "3. low": "0.0000", "4. close": "0.0000", "5. volume": "5961997"}, "2020-09-02": {"1. open": "0.0001", "2. high": "0.0001", "3. low": "0.0000", "4. close": "0.0000", "5. volume": "5961997"}, "2020-09-01": {"1. open": "0.0001", "2. high": "0.0001", "3. low": "0.0000", "4. close": "0.0000", "5. volume": "3547000"}, "2020-08-31": {"1. open": "0.0001", "2. high": "0.0001", "3. low": "0.0001", "4. close": "0.0001", "5. volume": "9000"}, "2020-08-28": {"1. open": "0.0001", "2. high": "0.0001", "3. low": "0.0001", "4. close": "0.0001", "5. volume": "12000"}, "2020-08-27": {"1. open": "0.0001", "2. high": "0.0001", "3. low": "0.0001", "4. close": "0.0001", "5. volume": "801000"}, "2020-08-26": {"1. open": "0.0001", "2. high": "0.0001", "3. low": "0.0001", "4. close": "0.0001", "5. volume": "503000"}, "2020-08-25": {"1. open": "0.0001", "2. high": "0.0001", "3. low": "0.0001", "4. close": "0.0001", "5. volume": "0"}, "2020-08-24": {"1. open": "0.0001", "2. high": "0.0001", "3. low": "0.0001", "4. close": "0.0001", "5. volume": "136"}, "2020-08-21": {"1. open": "0.0001", "2. high": "0.0001", "3. low": "0.0001", "4. close": "0.0001", "5. volume": "0"}, "2020-08-20": {"1. open": "0.0001", "2. high": "0.0001", "3. low": "0.0001", "4. close": "0.0001", "5. volume": "110000"}, "2020-08-19": {"1. open": "0.0001", "2. high": "0.0001", "3. low": "0.0001", "4. close": "0.0001", "5. volume": "0"}, "2020-08-18": {"1. open": "0.0001", "2. high": "0.0001", "3. low": "0.0001", "4. close": "0.0001", "5. volume": "0"}, "2020-08-17": {"1. open": "0.0001", "2. high": "0.0001", "3. low": "0.0001", "4. close": "0.0001", "5. volume": "0"}, "2020-08-14": {"1. open": "0.0001", "2. high": "0.0001", "3. low": "0.0001", "4. close": "0.0001", "5. volume": "0"}, "2020-08-13": {"1. open": "0.0001", "2. high": "0.0001", "3. low": "0.0001", "4. close": "0.0001", "5. volume": "0"}, "2020-08-12": {"1. open": "0.0001", "2. high": "0.0001", "3. low": "0.0001", "4. close": "0.0001", "5. volume": "0"}, "2020-08-11": {"1. open": "0.0001", "2. high": "0.0001", "3. low": "0.0001", "4. close": "0.0001", "5. volume": "0"}, "2020-08-10": {"1. open": "0.0001", "2. high": "0.0001", "3. low": "0.0001", "4. close": "0.0001", "5. volume": "0"}, "2020-08-07": {"1. open": "0.0001", "2. high": "0.0001", "3. low": "0.0001", "4. close": "0.0001", "5. volume": "100000"}, "2020-08-06": {"1. open": "0.0001", "2. high": "0.0001", "3. low": "0.0001", "4. close": "0.0001", "5. volume": "0"}, "2020-08-05": {"1. open": "0.0001", "2. high": "0.0001", "3. low": "0.0001", "4. close": "0.0001", "5. volume": "0"}, "2020-08-04": {"1. open": "0.0001", "2. high": "0.0001", "3. low": "0.0001", "4. close": "0.0001", "5. volume": "0"}, "2020-08-03": {"1. open": "0.0001", "2. high": "0.0001", "3. low": "0.0001", "4. close": "0.0001", "5. volume": "2000001"}, "2020-07-31": {"1. open": "0.0001", "2. high": "0.0001", "3. low": "0.0001", "4. close": "0.0001", "5. volume": "0"}, "2020-07-30": {"1. open": "0.0001", "2. high": "0.0001", "3. low": "0.0001", "4. close": "0.0001", "5. volume": "40002"}, "2020-07-29": {"1. open": "0.0000", "2. high": "0.0000", "3. low": "0.0000", "4. close": "0.0000", "5. volume": "100000"}, "2020-07-28": {"1. open": "0.0001", "2. high": "0.0001", "3. low": "0.0001", "4. close": "0.0001", "5. volume": "0"}, "2020-07-27": {"1. open": "0.0001", "2. high": "0.0001", "3. low": "0.0001", "4. close": "0.0001", "5. volume": "2249"}, "2020-07-24": {"1. open": "0.0001", "2. high": "0.0001", "3. low": "0.0001", "4. close": "0.0001", "5. volume": "0"}, "2020-07-23": {"1. open": "0.0001", "2. high": "0.0001", "3. low": "0.0001", "4. close": "0.0001", "5. volume": "100000"}, "2020-07-22": {"1. open": "0.0001", "2. high": "0.0001", "3. low": "0.0001", "4. close": "0.0001", "5. volume": "0"}, "2020-07-21": {"1. open": "0.0001", "2. high": "0.0001", "3. low": "0.0001", "4. close": "0.0001", "5. volume": "100000"}, "2020-07-17": {"1. open": "0.0001", "2. high": "0.0001", "3. low": "0.0001", "4. close": "0.0001", "5. volume": "1000000"}, "2020-07-08": {"1. open": "0.0001", "2. high": "0.0001", "3. low": "0.0001", "4. close": "0.0001", "5. volume": "105000"}, "2020-07-07": {"1. open": "0.0000", "2. high": "0.0001", "3. low": "0.0000", "4. close": "0.0000", "5. volume": "1050000"}, "2020-06-30": {"1. open": "0.0001", "2. high": "0.0001", "3. low": "0.0001", "4. close": "0.0001", "5. volume": "1200000"}, "2020-06-26": {"1. open": "0.0001", "2. high": "0.0001", "3. low": "0.0000", "4. close": "0.0000", "5. volume": "339013"}, "2020-06-25": {"1. open": "0.0001", "2. high": "0.0001", "3. low": "0.0001", "4. close": "0.0001", "5. volume": "4"}, "2020-06-24": {"1. open": "0.0001", "2. high": "0.0001", "3. low": "0.0001", "4. close": "0.0001", "5. volume": "1031310"}, "2020-06-22": {"1. open": "0.0001", "2. high": "0.0001", "3. low": "0.0001", "4. close": "0.0001", "5. volume": "200000"}, "2020-06-16": {"1. open": "0.0000", "2. high": "0.0001", "3. low": "0.0000", "4. close": "0.0000", "5. volume": "8500000"}, "2020-06-11": {"1. open": "0.0000", "2. high": "0.0000", "3. low": "0.0000", "4. close": "0.0000", "5. volume": "19"}, "2020-06-05": {"1. open": "0.0000", "2. high": "0.0000", "3. low": "0.0000", "4. close": "0.0000", "5. volume": "1500000"}, "2020-05-26": {"1. open": "0.0000", "2. high": "0.0000", "3. low": "0.0000", "4. close": "0.0000", "5. volume": "5750650"}, "2020-05-15": {"1. open": "0.0000", "2. high": "0.0000", "3. low": "0.0000", "4. close": "0.0000", "5. volume": "2000000"}, "2020-05-14": {"1. open": "0.0001", "2. high": "0.0001", "3. low": "0.0001", "4. close": "0.0001", "5. volume": "1010000"}, "2020-05-13": {"1. open": "0.0000", "2. high": "0.0000", "3. low": "0.0000", "4. close": "0.0000", "5. volume": "1"}, "2020-04-28": {"1. open": "0.0000", "2. high": "0.0000", "3. low": "0.0000", "4. close": "0.0000", "5. volume": "500000"}, "2020-04-14": {"1. open": "0.0001", "2. high": "0.0001", "3. low": "0.0001", "4. close": "0.0001", "5. volume": "420006"}, "2020-04-13": {"1. open": "0.0001", "2. high": "0.0001", "3. low": "0.0000", "4. close": "0.0000", "5. volume": "77000"}, "2020-03-31": {"1. open": "0.0001", "2. high": "0.0001", "3. low": "0.0001", "4. close": "0.0001", "5. volume": "6"}, "2020-03-25": {"1. open": "0.0001", "2. high": "0.0001", "3. low": "0.0001", "4. close": "0.0001", "5. volume": "590000"}, "2020-03-24": {"1. open": "0.0001", "2. high": "0.0001", "3. low": "0.0001", "4. close": "0.0001", "5. volume": "300000"}, "2020-03-23": {"1. open": "0.0000", "2. high": "0.0000", "3. low": "0.0000", "4. close": "0.0000", "5. volume": "750000"}, "2020-03-16": {"1. open": "0.0001", "2. high": "0.0001", "3. low": "0.0001", "4. close": "0.0001", "5. volume": "2"}, "2020-02-26": {"1. open": "0.0001", "2. high": "0.0001", "3. low": "0.0001", "4. close": "0.0001", "5. volume": "440000"}, "2020-02-07": {"1. open": "0.0001", "2. high": "0.0001", "3. low": "0.0001", "4. close": "0.0001", "5. volume": "600"}, "2020-01-28": {"1. open": "0.0001", "2. high": "0.0001", "3. low": "0.0001", "4. close": "0.0001", "5. volume": "2011"}, "2020-01-23": {"1. open": "0.0001", "2. high": "0.0001", "3. low": "0.0001", "4. close": "0.0001", "5. volume": "30"}, "2020-01-17": {"1. open": "0.0001", "2. high": "0.0001", "3. low": "0.0001", "4. close": "0.0001", "5. volume": "1003"}, "2020-01-13": {"1. open": "0.0001", "2. high": "0.0001", "3. low": "0.0001", "4. close": "0.0001", "5. volume": "3089"}, "2020-01-07": {"1. open": "0.0001", "2. high": "0.0001", "3. low": "0.0001", "4. close": "0.0001", "5. volume": "32080"}, "2019-12-23": {"1. open": "0.0001", "2. high": "0.0001", "3. low": "0.0001", "4. close": "0.0001", "5. volume": "200000"}, "2019-12-18": {"1. open": "0.0001", "2. high": "0.0001", "3. low": "0.0001", "4. close": "0.0001", "5. volume": "14"}, "2019-12-13": {"1. open": "0.0001", "2. high": "0.0001", "3. low": "0.0000", "4. close": "0.0000", "5. volume": "7000000"}, "2019-12-06": {"1. open": "0.0001", "2. high": "0.0001", "3. low": "0.0001", "4. close": "0.0001", "5. volume": "1253"}, "2019-11-29": {"1. open": "0.0000", "2. high": "0.0000", "3. low": "0.0000", "4. close": "0.0000", "5. volume": "1030000"}, "2019-11-11": {"1. open": "0.0001", "2. high": "0.0001", "3. low": "0.0001", "4. close": "0.0001", "5. volume": "1200"}, "2019-11-06": {"1. open": "0.0001", "2. high": "0.0001", "3. low": "0.0001", "4. close": "0.0001", "5. volume": "1"}, "2019-11-01": {"1. open": "0.0001", "2. high": "0.0001", "3. low": "0.0001", "4. close": "0.0001", "5. volume": "2800000"}, "2019-10-30": {"1. open": "0.0001", "2. high": "0.0001", "3. low": "0.0001", "4. close": "0.0001", "5. volume": "200000"}, "2019-10-22": {"1. open": "0.0001", "2. high": "0.0001", "3. low": "0.0001", "4. close": "0.0001", "5. volume": "5"}, "2019-10-21": {"1. open": "0.0001", "2. high": "0.0001", "3. low": "0.0001", "4. close": "0.0001", "5. volume": "1000000"}, "2019-09-17": {"1. open": "0.0000", "2. high": "0.0001", "3. low": "0.0000", "4. close": "0.0000", "5. volume": "214109"}, "2019-09-16": {"1. open": "0.0001", "2. high": "0.0001", "3. low": "0.0001", "4. close": "0.0001", "5. volume": "17"}, "2019-08-28": {"1. open": "0.0001", "2. high": "0.0001", "3. low": "0.0000", "4. close": "0.0000", "5. volume": "3000000"}, "2019-08-26": {"1. open": "0.0001", "2. high": "0.0001", "3. low": "0.0001", "4. close": "0.0001", "5. volume": "4"}, "2019-08-20": {"1. open": "0.0001", "2. high": "0.0001", "3. low": "0.0001", "4. close": "0.0001", "5. volume": "56"}, "2019-08-19": {"1. open": "0.0001", "2. high": "0.0001", "3. low": "0.0001", "4. close": "0.0001", "5. volume": "12000"}, "2019-08-15": {"1. open": "0.0001", "2. high": "0.0001", "3. low": "0.0001", "4. close": "0.0001", "5. volume": "1700000"}, "2019-08-14": {"1. open": "0.0001", "2. high": "0.0001", "3. low": "0.0001", "4. close": "0.0001", "5. volume": "10000"}, "2019-08-07": {"1. open": "0.0000", "2. high": "0.0000", "3. low": "0.0000", "4. close": "0.0000", "5. volume": "250000"}, "2019-07-29": {"1. open": "0.0001", "2. high": "0.0001", "3. low": "0.0001", "4. close": "0.0001", "5. volume": "34"}, "2019-07-26": {"1. open": "0.0001", "2. high": "0.0001", "3. low": "0.0001", "4. close": "0.0001", "5. volume": "126010"}, "2019-07-25": {"1. open": "0.0001", "2. high": "0.0001", "3. low": "0.0000", "4. close": "0.0000", "5. volume": "15000"}, "2019-07-17": {"1. open": "0.0001", "2. high": "0.0001", "3. low": "0.0001", "4. close": "0.0001", "5. volume": "31050000"}, "2019-07-16": {"1. open": "0.0000", "2. high": "0.0000", "3. low": "0.0000", "4. close": "0.0000", "5. volume": "1"}, "2019-07-09": {"1. open": "0.0000", "2. high": "0.0000", "3. low": "0.0000", "4. close": "0.0000", "5. volume": "30"}, "2019-07-02": {"1. open": "0.0000", "2. high": "0.0000", "3. low": "0.0000", "4. close": "0.0000", "5. volume": "600"}, "2019-06-19": {"1. open": "0.0001", "2. high": "0.0001", "3. low": "0.0001", "4. close": "0.0001", "5. volume": "30"}, "2019-06-10": {"1. open": "0.0001", "2. high": "0.0001", "3. low": "0.0001", "4. close": "0.0001", "5. volume": "200013"}, "2019-06-07": {"1. open": "0.0000", "2. high": "0.0001", "3. low": "0.0000", "4. close": "0.0000", "5. volume": "1033000"}, "2019-05-29": {"1. open": "0.0000", "2. high": "0.0001", "3. low": "0.0000", "4. close": "0.0000", "5. volume": "812500"}, "2019-05-17": {"1. open": "0.0001", "2. high": "0.0001", "3. low": "0.0001", "4. close": "0.0001", "5. volume": "100000"}, "2019-05-16": {"1. open": "0.0001", "2. high": "0.0001", "3. low": "0.0001", "4. close": "0.0001", "5. volume": "20045"}, "2019-05-15": {"1. open": "0.0000", "2. high": "0.0000", "3. low": "0.0000", "4. close": "0.0000", "5. volume": "141013"}, "2019-05-14": {"1. open": "0.0000", "2. high": "0.0000", "3. low": "0.0000", "4. close": "0.0000", "5. volume": "273129"}, "2019-05-08": {"1. open": "0.0001", "2. high": "0.0001", "3. low": "0.0001", "4. close": "0.0001", "5. volume": "3050000"}, "2019-05-06": {"1. open": "0.0000", "2. high": "0.0000", "3. low": "0.0000", "4. close": "0.0000", "5. volume": "1000000"}, "2019-04-16": {"1. open": "0.0001", "2. high": "0.0001", "3. low": "0.0001", "4. close": "0.0001", "5. volume": "100000"}, "2019-04-15": {"1. open": "0.0000", "2. high": "0.0000", "3. low": "0.0000", "4. close": "0.0000", "5. volume": "83333"}, "2019-03-18": {"1. open": "0.0001", "2. high": "0.0001", "3. low": "0.0001", "4. close": "0.0001", "5. volume": "100000"}, "2019-03-15": {"1. open": "0.0000", "2. high": "0.0000", "3. low": "0.0000", "4. close": "0.0000", "5. volume": "450000"}, "2019-02-04": {"1. open": "0.0001", "2. high": "0.0001", "3. low": "0.0001", "4. close": "0.0001", "5. volume": "650000"}, "2019-01-28": {"1. open": "0.0000", "2. high": "0.0000", "3. low": "0.0000", "4. close": "0.0000", "5. volume": "50000"}, "2019-01-14": {"1. open": "0.0000", "2. high": "0.0000", "3. low": "0.0000", "4. close": "0.0000", "5. volume": "6315676"}, "2019-01-07": {"1. open": "0.0001", "2. high": "0.0001", "3. low": "0.0001", "4. close": "0.0001", "5. volume": "2"}, "2018-12-13": {"1. open": "0.0000", "2. high": "0.0000", "3. low": "0.0000", "4. close": "0.0000", "5. volume": "2988089"}, "2018-11-30": {"1. open": "0.0000", "2. high": "0.0000", "3. low": "0.0000", "4. close": "0.0000", "5. volume": "1501"}, "2018-11-28": {"1. open": "0.0001", "2. high": "0.0001", "3. low": "0.0001", "4. close": "0.0001", "5. volume": "9"}, "2018-11-23": {"1. open": "0.0001", "2. high": "0.0001", "3. low": "0.0001", "4. close": "0.0001", "5. volume": "10100"}, "2018-11-21": {"1. open": "0.0001", "2. high": "0.0001", "3. low": "0.0001", "4. close": "0.0001", "5. volume": "1"}, "2018-10-30": {"1. open": "0.0001", "2. high": "0.0001", "3. low": "0.0001", "4. close": "0.0001", "5. volume": "4"}, "2018-10-16": {"1. open": "0.0001", "2. high": "0.0001", "3. low": "0.0001", "4. close": "0.0001", "5. volume": "31"}, "2018-10-10": {"1. open": "0.0001", "2. high": "0.0001", "3. low": "0.0001", "4. close": "0.0001", "5. volume": "5"}, "2018-10-08": {"1. open": "0.0001", "2. high": "0.0001", "3. low": "0.0001", "4. close": "0.0001", "5. volume": "1000000"}, "2018-10-05": {"1. open": "0.0001", "2. high": "0.0001", "3. low": "0.0001", "4. close": "0.0001", "5. volume": "9824999"}, "2018-10-01": {"1. open": "0.0001", "2. high": "0.0001", "3. low": "0.0001", "4. close": "0.0001", "5. volume": "33000"}, "2018-09-28": {"1. open": "0.0000", "2. high": "0.0000", "3. low": "0.0000", "4. close": "0.0000", "5. volume": "2000000"}, "2018-09-19": {"1. open": "0.0001", "2. high": "0.0001", "3. low": "0.0001", "4. close": "0.0001", "5. volume": "1"}, "2018-09-14": {"1. open": "0.0001", "2. high": "0.0001", "3. low": "0.0001", "4. close": "0.0001", "5. volume": "2603001"}, "2018-08-29": {"1. open": "0.0001", "2. high": "0.0001", "3. low": "0.0001", "4. close": "0.0001", "5. volume": "2700000"}, "2018-08-28": {"1. open": "0.0000", "2. high": "0.0000", "3. low": "0.0000", "4. close": "0.0000", "5. volume": "250000"}, "2018-07-27": {"1. open": "0.0001", "2. high": "0.0001", "3. low": "0.0001", "4. close": "0.0001", "5. volume": "500"}, "2018-07-24": {"1. open": "0.0001", "2. high": "0.0001", "3. low": "0.0001", "4. close": "0.0001", "5. volume": "4500000"}, "2018-07-09": {"1. open": "0.0001", "2. high": "0.0001", "3. low": "0.0001", "4. close": "0.0001", "5. volume": "1500000"}, "2018-06-15": {"1. open": "0.0001", "2. high": "0.0001", "3. low": "0.0001", "4. close": "0.0001", "5. volume": "4"}, "2018-06-14": {"1. open": "0.0001", "2. high": "0.0001", "3. low": "0.0001", "4. close": "0.0001", "5. volume": "5"}, "2018-06-04": {"1. open": "0.0001", "2. high": "0.0001", "3. low": "0.0001", "4. close": "0.0001", "5. volume": "1300000"}, "2018-05-29": {"1. open": "0.0001", "2. high": "0.0001", "3. low": "0.0001", "4. close": "0.0001", "5. volume": "10399993"}, "2018-05-25": {"1. open": "0.0001", "2. high": "0.0002", "3. low": "0.0001", "4. close": "0.0001", "5. volume": "241645521"}, "2018-05-24": {"1. open": "0.0001", "2. high": "0.0001", "3. low": "0.0001", "4. close": "0.0001", "5. volume": "23490000"}, "2018-05-23": {"1. open": "0.0001", "2. high": "0.0001", "3. low": "0.0001", "4. close": "0.0001", "5. volume": "1"}, "2018-05-21": {"1. open": "0.0001", "2. high": "0.0001", "3. low": "0.0001", "4. close": "0.0001", "5. volume": "5000000"}, "2018-05-18": {"1. open": "0.0001", "2. high": "0.0001", "3. low": "0.0001", "4. close": "0.0001", "5. volume": "1011822"}, "2018-05-11": {"1. open": "0.0001", "2. high": "0.0001", "3. low": "0.0001", "4. close": "0.0001", "5. volume": "2000911"}, "2018-05-09": {"1. open": "0.0001", "2. high": "0.0001", "3. low": "0.0001", "4. close": "0.0001", "5. volume": "60604"}, "2018-04-27": {"1. open": "0.0001", "2. high": "0.0001", "3. low": "0.0001", "4. close": "0.0001", "5. volume": "4"}, "2018-04-23": {"1. open": "0.0001", "2. high": "0.0001", "3. low": "0.0001", "4. close": "0.0001", "5. volume": "3243153"}, "2018-04-11": {"1. open": "0.0001", "2. high": "0.0001", "3. low": "0.0001", "4. close": "0.0001", "5. volume": "21822"}, "2018-04-05": {"1. open": "0.0001", "2. high": "0.0001", "3. low": "0.0001", "4. close": "0.0001", "5. volume": "3000002"}, "2018-03-14": {"1. open": "0.0001", "2. high": "0.0001", "3. low": "0.0001", "4. close": "0.0001", "5. volume": "5103633"}, "2018-03-06": {"1. open": "0.0001", "2. high": "0.0001", "3. low": "0.0001", "4. close": "0.0001", "5. volume": "730000"}, "2018-03-01": {"1. open": "0.0001", "2. high": "0.0001", "3. low": "0.0001", "4. close": "0.0001", "5. volume": "15794886"}, "2018-02-28": {"1. open": "0.0000", "2. high": "0.0001", "3. low": "0.0000", "4. close": "0.0000", "5. volume": "155008"}, "2018-02-26": {"1. open": "0.0001", "2. high": "0.0001", "3. low": "0.0001", "4. close": "0.0001", "5. volume": "20534343"}, "2018-02-20": {"1. open": "0.0001", "2. high": "0.0001", "3. low": "0.0001", "4. close": "0.0001", "5. volume": "3500000"}, "2018-02-15": {"1. open": "0.0001", "2. high": "0.0001", "3. low": "0.0001", "4. close": "0.0001", "5. volume": "3515000"}, "2018-02-14": {"1. open": "0.0001", "2. high": "0.0001", "3. low": "0.0001", "4. close": "0.0001", "5. volume": "210650059"}, "2018-02-07": {"1. open": "0.0001", "2. high": "0.0001", "3. low": "0.0001", "4. close": "0.0001", "5. volume": "6"}, "2018-02-02": {"1. open": "0.0001", "2. high": "0.0001", "3. low": "0.0001", "4. close": "0.0001", "5. volume": "1"}, "2018-01-29": {"1. open": "0.0001", "2. high": "0.0001", "3. low": "0.0001", "4. close": "0.0001", "5. volume": "7000000"}, "2018-01-23": {"1. open": "0.0001", "2. high": "0.0001", "3. low": "0.0001", "4. close": "0.0001", "5. volume": "405000"}, "2018-01-12": {"1. open": "0.0001", "2. high": "0.0001", "3. low": "0.0001", "4. close": "0.0001", "5. volume": "156222"}, "2018-01-11": {"1. open": "0.0001", "2. high": "0.0001", "3. low": "0.0001", "4. close": "0.0001", "5. volume": "10089"}, "2018-01-03": {"1. open": "0.0000", "2. high": "0.0001", "3. low": "0.0000", "4. close": "0.0000", "5. volume": "110300"}, "2018-01-02": {"1. open": "0.0001", "2. high": "0.0001", "3. low": "0.0001", "4. close": "0.0001", "5. volume": "3100012"}, "2017-12-29": {"1. open": "0.0001", "2. high": "0.0001", "3. low": "0.0001", "4. close": "0.0001", "5. volume": "780000"}, "2017-12-28": {"1. open": "0.0001", "2. high": "0.0001", "3. low": "0.0001", "4. close": "0.0001", "5. volume": "10"}, "2017-12-27": {"1. open": "0.0001", "2. high": "0.0001", "3. low": "0.0001", "4. close": "0.0001", "5. volume": "2000000"}, "2017-12-26": {"1. open": "0.0001", "2. high": "0.0001", "3. low": "0.0001", "4. close": "0.0001", "5. volume": "100110"}, "2017-12-21": {"1. open": "0.0001", "2. high": "0.0001", "3. low": "0.0001", "4. close": "0.0001", "5. volume": "3"}, "2017-12-20": {"1. open": "0.0001", "2. high": "0.0001", "3. low": "0.0001", "4. close": "0.0001", "5. volume": "687144"}, "2017-12-19": {"1. open": "0.0001", "2. high": "0.0001", "3. low": "0.0001", "4. close": "0.0001", "5. volume": "670003"}, "2017-12-18": {"1. open": "0.0001", "2. high": "0.0001", "3. low": "0.0001", "4. close": "0.0001", "5. volume": "388028"}, "2017-12-15": {"1. open": "0.0001", "2. high": "0.0001", "3. low": "0.0001", "4. close": "0.0001", "5. volume": "3435003"}, "2017-12-14": {"1. open": "0.0001", "2. high": "0.0001", "3. low": "0.0001", "4. close": "0.0001", "5. volume": "27235477"}, "2017-12-13": {"1. open": "0.0001", "2. high": "0.0001", "3. low": "0.0001", "4. close": "0.0001", "5. volume": "210000"}, "2017-12-12": {"1. open": "0.0000", "2. high": "0.0000", "3. low": "0.0000", "4. close": "0.0000", "5. volume": "3187569"}, "2017-12-11": {"1. open": "0.0001", "2. high": "0.0001", "3. low": "0.0001", "4. close": "0.0001", "5. volume": "1002000"}, "2017-12-08": {"1. open": "0.0001", "2. high": "0.0001", "3. low": "0.0000", "4. close": "0.0000", "5. volume": "7319461"}, "2017-12-06": {"1. open": "0.0001", "2. high": "0.0001", "3. low": "0.0001", "4. close": "0.0001", "5. volume": "150002"}, "2017-11-21": {"1. open": "0.0001", "2. high": "0.0001", "3. low": "0.0001", "4. close": "0.0001", "5. volume": "4"}, "2017-11-09": {"1. open": "0.0001", "2. high": "0.0001", "3. low": "0.0001", "4. close": "0.0001", "5. volume": "64699891"}, "2017-11-01": {"1. open": "0.0001", "2. high": "0.0001", "3. low": "0.0001", "4. close": "0.0001", "5. volume": "10000"}, "2017-10-30": {"1. open": "0.0000", "2. high": "0.0000", "3. low": "0.0000", "4. close": "0.0000", "5. volume": "800000"}, "2017-10-24": {"1. open": "0.0001", "2. high": "0.0001", "3. low": "0.0001", "4. close": "0.0001", "5. volume": "2"}, "2017-10-20": {"1. open": "0.0001", "2. high": "0.0001", "3. low": "0.0001", "4. close": "0.0001", "5. volume": "0"}, "2017-10-19": {"1. open": "0.0001", "2. high": "0.0001", "3. low": "0.0001", "4. close": "0.0001", "5. volume": "97500"}, "2017-10-18": {"1. open": "0.0001", "2. high": "0.0001", "3. low": "0.0001", "4. close": "0.0001", "5. volume": "2100000"}, "2017-10-12": {"1. open": "0.0001", "2. high": "0.0001", "3. low": "0.0001", "4. close": "0.0001", "5. volume": "7000000"}, "2017-10-10": {"1. open": "0.0001", "2. high": "0.0001", "3. low": "0.0001", "4. close": "0.0001", "5. volume": "3"}, "2017-09-27": {"1. open": "0.0001", "2. high": "0.0001", "3. low": "0.0001", "4. close": "0.0001", "5. volume": "101134"}, "2017-09-26": {"1. open": "0.0000", "2. high": "0.0001", "3. low": "0.0000", "4. close": "0.0000", "5. volume": "30782"}, "2017-09-22": {"1. open": "0.0001", "2. high": "0.0001", "3. low": "0.0001", "4. close": "0.0001", "5. volume": "160000"}}}