{"Meta Data": {"1. Information": "Daily Prices (open, high, low, close) and Volumes", "2. Symbol": "UPST", "3. Last Refreshed": "2022-02-07 16:00:01", "4. Output Size": "Full size", "5. Time Zone": "US/Eastern"}, "Time Series (Daily)": {"2022-02-07": {"1. open": "99.4900", "2. high": "105.1400", "3. low": "95.3000", "4. close": "96.0400", "5. volume": "4926945"}, "2022-02-04": {"1. open": "99.5700", "2. high": "101.4000", "3. low": "93.2200", "4. close": "98.6300", "5. volume": "6249869"}, "2022-02-03": {"1. open": "99.6300", "2. high": "105.2000", "3. low": "97.1000", "4. close": "97.9300", "5. volume": "5422846"}, "2022-02-02": {"1. open": "115.0400", "2. high": "116.4000", "3. low": "103.1100", "4. close": "105.7900", "5. volume": "7537776"}, "2022-02-01": {"1. open": "111.3000", "2. high": "120.7480", "3. low": "106.4000", "4. close": "117.3300", "5. volume": "11496993"}, "2022-01-31": {"1. open": "96.1700", "2. high": "110.0100", "3. low": "95.0000", "4. close": "109.0100", "5. volume": "6743996"}, "2022-01-28": {"1. open": "89.0400", "2. high": "96.6900", "3. low": "87.2600", "4. close": "95.0000", "5. volume": "6893487"}, "2022-01-27": {"1. open": "100.5000", "2. high": "103.0000", "3. low": "87.0300", "4. close": "90.1300", "5. volume": "9377020"}, "2022-01-26": {"1. open": "98.2300", "2. high": "106.0696", "3. low": "94.0000", "4. close": "96.0500", "5. volume": "9932891"}, "2022-01-25": {"1. open": "88.6400", "2. high": "98.2700", "3. low": "88.3400", "4. close": "94.2000", "5. volume": "7108285"}, "2022-01-24": {"1. open": "86.4011", "2. high": "92.1500", "3. low": "75.1500", "4. close": "91.3600", "5. volume": "12901358"}, "2022-01-21": {"1. open": "105.0020", "2. high": "106.2799", "3. low": "91.8300", "4. close": "92.7200", "5. volume": "9072056"}, "2022-01-20": {"1. open": "108.0000", "2. high": "117.7600", "3. low": "106.6000", "4. close": "107.1500", "5. volume": "5544075"}, "2022-01-19": {"1. open": "110.5300", "2. high": "112.8800", "3. low": "105.4900", "4. close": "106.0100", "5. volume": "3918535"}, "2022-01-18": {"1. open": "107.5000", "2. high": "115.2800", "3. low": "105.3000", "4. close": "109.9100", "5. volume": "5926028"}, "2022-01-14": {"1. open": "107.8500", "2. high": "114.2811", "3. low": "107.6285", "4. close": "111.1100", "5. volume": "4903488"}, "2022-01-13": {"1. open": "119.2800", "2. high": "120.9700", "3. low": "108.5600", "4. close": "109.2500", "5. volume": "4647158"}, "2022-01-12": {"1. open": "125.6000", "2. high": "128.2899", "3. low": "117.1975", "4. close": "118.4100", "5. volume": "5298826"}, "2022-01-11": {"1. open": "113.3500", "2. high": "124.6500", "3. low": "112.1000", "4. close": "121.0600", "5. volume": "5287755"}, "2022-01-10": {"1. open": "113.5100", "2. high": "114.6099", "3. low": "107.2900", "4. close": "114.4200", "5. volume": "8062185"}, "2022-01-07": {"1. open": "119.0300", "2. high": "125.2500", "3. low": "114.5767", "4. close": "116.9500", "5. volume": "5847460"}, "2022-01-06": {"1. open": "122.5000", "2. high": "124.3000", "3. low": "113.3200", "4. close": "118.4300", "5. volume": "7782471"}, "2022-01-05": {"1. open": "135.1220", "2. high": "142.7400", "3. low": "123.1000", "4. close": "123.8200", "5. volume": "6367836"}, "2022-01-04": {"1. open": "144.9100", "2. high": "146.8300", "3. low": "133.3400", "4. close": "136.5800", "5. volume": "5711668"}, "2022-01-03": {"1. open": "153.6200", "2. high": "155.6000", "3. low": "144.1200", "4. close": "144.6600", "5. volume": "3554680"}, "2021-12-31": {"1. open": "153.2300", "2. high": "156.9000", "3. low": "151.0700", "4. close": "151.3000", "5. volume": "2496395"}, "2021-12-30": {"1. open": "147.2700", "2. high": "162.7644", "3. low": "146.4000", "4. close": "155.4300", "5. volume": "5677738"}, "2021-12-29": {"1. open": "148.9100", "2. high": "150.5273", "3. low": "141.0600", "4. close": "147.9000", "5. volume": "3769886"}, "2021-12-28": {"1. open": "162.1100", "2. high": "162.8144", "3. low": "147.8000", "4. close": "148.9700", "5. volume": "5138978"}, "2021-12-27": {"1. open": "151.5200", "2. high": "163.2000", "3. low": "150.8100", "4. close": "160.0400", "5. volume": "5085168"}, "2021-12-23": {"1. open": "145.7500", "2. high": "149.5600", "3. low": "142.5700", "4. close": "148.1400", "5. volume": "2565861"}, "2021-12-22": {"1. open": "145.4467", "2. high": "150.8199", "3. low": "142.2200", "4. close": "145.2800", "5. volume": "4402235"}, "2021-12-21": {"1. open": "135.4300", "2. high": "150.8300", "3. low": "134.2000", "4. close": "149.4800", "5. volume": "5556147"}, "2021-12-20": {"1. open": "134.0150", "2. high": "136.4700", "3. low": "129.5000", "4. close": "131.5000", "5. volume": "4792528"}, "2021-12-17": {"1. open": "136.7076", "2. high": "140.8648", "3. low": "128.4500", "4. close": "139.1800", "5. volume": "6523630"}, "2021-12-16": {"1. open": "158.0780", "2. high": "159.7000", "3. low": "138.1100", "4. close": "140.6400", "5. volume": "6866153"}, "2021-12-15": {"1. open": "144.8749", "2. high": "156.3899", "3. low": "141.0000", "4. close": "154.2300", "5. volume": "6309170"}, "2021-12-14": {"1. open": "147.0000", "2. high": "147.8900", "3. low": "137.8500", "4. close": "144.9500", "5. volume": "8425948"}, "2021-12-13": {"1. open": "160.7900", "2. high": "163.7899", "3. low": "149.4350", "4. close": "151.0600", "5. volume": "6843274"}, "2021-12-10": {"1. open": "180.8027", "2. high": "183.1737", "3. low": "159.0400", "4. close": "160.7500", "5. volume": "7049853"}, "2021-12-09": {"1. open": "192.0000", "2. high": "197.1800", "3. low": "176.8300", "4. close": "179.6000", "5. volume": "4463835"}, "2021-12-08": {"1. open": "193.2100", "2. high": "199.8000", "3. low": "182.8300", "4. close": "194.3700", "5. volume": "4457701"}, "2021-12-07": {"1. open": "183.2100", "2. high": "198.0200", "3. low": "181.1200", "4. close": "193.8800", "5. volume": "4981413"}, "2021-12-06": {"1. open": "166.9000", "2. high": "180.7100", "3. low": "157.2600", "4. close": "176.1600", "5. volume": "4783662"}, "2021-12-03": {"1. open": "187.6800", "2. high": "191.7599", "3. low": "167.6700", "4. close": "171.5900", "5. volume": "7713525"}, "2021-12-02": {"1. open": "179.6500", "2. high": "185.0000", "3. low": "159.6600", "4. close": "177.0000", "5. volume": "10661260"}, "2021-12-01": {"1. open": "206.2900", "2. high": "209.0300", "3. low": "176.0035", "4. close": "179.6500", "5. volume": "6304101"}, "2021-11-30": {"1. open": "213.1100", "2. high": "220.2100", "3. low": "204.1500", "4. close": "204.8900", "5. volume": "4677505"}, "2021-11-29": {"1. open": "214.9300", "2. high": "217.4123", "3. low": "201.7208", "4. close": "212.5100", "5. volume": "3665120"}, "2021-11-26": {"1. open": "200.0800", "2. high": "212.6700", "3. low": "200.0800", "4. close": "209.4100", "5. volume": "2185140"}, "2021-11-24": {"1. open": "191.2856", "2. high": "210.0100", "3. low": "190.2300", "4. close": "207.6000", "5. volume": "4320503"}, "2021-11-23": {"1. open": "203.8300", "2. high": "205.9899", "3. low": "189.0000", "4. close": "197.3600", "5. volume": "5666837"}, "2021-11-22": {"1. open": "210.7400", "2. high": "215.2900", "3. low": "197.5510", "4. close": "205.4900", "5. volume": "5857508"}, "2021-11-19": {"1. open": "227.5200", "2. high": "228.6300", "3. low": "205.2900", "4. close": "206.9700", "5. volume": "6476804"}, "2021-11-18": {"1. open": "234.6400", "2. high": "238.4500", "3. low": "223.0100", "4. close": "226.3700", "5. volume": "3495231"}, "2021-11-17": {"1. open": "235.6900", "2. high": "247.7000", "3. low": "231.3200", "4. close": "232.0200", "5. volume": "2974969"}, "2021-11-16": {"1. open": "230.6900", "2. high": "241.0000", "3. low": "227.1000", "4. close": "236.0100", "5. volume": "4008370"}, "2021-11-15": {"1. open": "260.5180", "2. high": "261.9900", "3. low": "232.5000", "4. close": "233.7800", "5. volume": "7801638"}, "2021-11-12": {"1. open": "246.4604", "2. high": "265.7000", "3. low": "244.8000", "4. close": "264.1800", "5. volume": "5350988"}, "2021-11-11": {"1. open": "264.4900", "2. high": "265.9899", "3. low": "243.5000", "4. close": "246.0200", "5. volume": "5351441"}, "2021-11-10": {"1. open": "242.7500", "2. high": "270.8699", "3. low": "239.9800", "4. close": "256.5900", "5. volume": "14442647"}, "2021-11-09": {"1. open": "334.0000", "2. high": "338.5000", "3. low": "307.8600", "4. close": "313.7100", "5. volume": "5280365"}, "2021-11-08": {"1. open": "340.9000", "2. high": "342.5100", "3. low": "321.3000", "4. close": "334.6000", "5. volume": "3152321"}, "2021-11-05": {"1. open": "325.0000", "2. high": "334.9900", "3. low": "320.2500", "4. close": "331.5600", "5. volume": "2469534"}, "2021-11-04": {"1. open": "328.2500", "2. high": "337.0000", "3. low": "320.3301", "4. close": "321.7100", "5. volume": "2233367"}, "2021-11-03": {"1. open": "343.2810", "2. high": "343.3000", "3. low": "320.2000", "4. close": "330.1100", "5. volume": "3148671"}, "2021-11-02": {"1. open": "348.0000", "2. high": "355.4200", "3. low": "332.8800", "4. close": "344.0900", "5. volume": "2595493"}, "2021-11-01": {"1. open": "323.7800", "2. high": "346.8800", "3. low": "323.0200", "4. close": "344.7300", "5. volume": "3500821"}, "2021-10-29": {"1. open": "329.3700", "2. high": "340.9900", "3. low": "318.4800", "4. close": "322.0400", "5. volume": "2804819"}, "2021-10-28": {"1. open": "328.1700", "2. high": "336.7600", "3. low": "321.4601", "4. close": "330.0000", "5. volume": "3087693"}, "2021-10-27": {"1. open": "320.0000", "2. high": "334.8100", "3. low": "311.5000", "4. close": "314.5000", "5. volume": "3677034"}, "2021-10-26": {"1. open": "352.5609", "2. high": "355.7199", "3. low": "310.0200", "4. close": "327.0800", "5. volume": "7312937"}, "2021-10-25": {"1. open": "348.6569", "2. high": "362.6999", "3. low": "345.5000", "4. close": "359.8100", "5. volume": "3226546"}, "2021-10-22": {"1. open": "351.7800", "2. high": "353.8800", "3. low": "336.6600", "4. close": "342.5600", "5. volume": "3695909"}, "2021-10-21": {"1. open": "356.7100", "2. high": "370.2599", "3. low": "352.8200", "4. close": "354.3400", "5. volume": "2845060"}, "2021-10-20": {"1. open": "364.5000", "2. high": "368.9794", "3. low": "351.5000", "4. close": "355.8200", "5. volume": "3842943"}, "2021-10-19": {"1. open": "388.3100", "2. high": "394.9800", "3. low": "362.8000", "4. close": "367.0800", "5. volume": "4634205"}, "2021-10-18": {"1. open": "369.2300", "2. high": "389.2999", "3. low": "357.4717", "4. close": "383.2100", "5. volume": "7331648"}, "2021-10-15": {"1. open": "385.0000", "2. high": "401.4899", "3. low": "380.6000", "4. close": "390.0000", "5. volume": "8525467"}, "2021-10-14": {"1. open": "351.9100", "2. high": "380.2184", "3. low": "347.5700", "4. close": "379.6800", "5. volume": "6764001"}, "2021-10-13": {"1. open": "337.7000", "2. high": "345.6900", "3. low": "328.3600", "4. close": "344.8900", "5. volume": "4122592"}, "2021-10-12": {"1. open": "316.2300", "2. high": "337.5200", "3. low": "310.9300", "4. close": "333.0500", "5. volume": "4692116"}, "2021-10-11": {"1. open": "309.5100", "2. high": "319.0000", "3. low": "305.2600", "4. close": "310.9200", "5. volume": "2892767"}, "2021-10-08": {"1. open": "308.6400", "2. high": "316.1700", "3. low": "304.8100", "4. close": "311.2300", "5. volume": "2258639"}, "2021-10-07": {"1. open": "315.5000", "2. high": "323.5900", "3. low": "304.0000", "4. close": "307.3800", "5. volume": "3390003"}, "2021-10-06": {"1. open": "289.2500", "2. high": "313.6000", "3. low": "286.7800", "4. close": "307.7000", "5. volume": "4922333"}, "2021-10-05": {"1. open": "294.6138", "2. high": "303.9900", "3. low": "288.6523", "4. close": "296.3000", "5. volume": "3037538"}, "2021-10-04": {"1. open": "293.0749", "2. high": "296.8400", "3. low": "281.1301", "4. close": "289.7700", "5. volume": "3515365"}, "2021-10-01": {"1. open": "311.8335", "2. high": "315.5677", "3. low": "285.5500", "4. close": "298.7700", "5. volume": "5595676"}, "2021-09-30": {"1. open": "323.6823", "2. high": "327.6415", "3. low": "313.5001", "4. close": "316.4400", "5. volume": "3398756"}, "2021-09-29": {"1. open": "319.0100", "2. high": "332.1000", "3. low": "317.3300", "4. close": "320.0000", "5. volume": "4826713"}, "2021-09-28": {"1. open": "326.9100", "2. high": "326.9500", "3. low": "304.0000", "4. close": "313.4000", "5. volume": "5090233"}, "2021-09-27": {"1. open": "328.5000", "2. high": "342.2700", "3. low": "319.1800", "4. close": "331.9900", "5. volume": "4048030"}, "2021-09-24": {"1. open": "332.0500", "2. high": "337.2300", "3. low": "323.5900", "4. close": "327.8800", "5. volume": "3796854"}, "2021-09-23": {"1. open": "328.7728", "2. high": "346.5400", "3. low": "324.0000", "4. close": "336.3400", "5. volume": "5852626"}, "2021-09-22": {"1. open": "324.0000", "2. high": "334.4400", "3. low": "311.6700", "4. close": "323.5100", "5. volume": "6209433"}, "2021-09-21": {"1. open": "297.6400", "2. high": "329.4700", "3. low": "294.4200", "4. close": "320.7700", "5. volume": "8816717"}, "2021-09-20": {"1. open": "290.0000", "2. high": "303.9900", "3. low": "288.2700", "4. close": "293.4700", "5. volume": "5458302"}, "2021-09-17": {"1. open": "298.0000", "2. high": "308.7800", "3. low": "292.8600", "4. close": "303.3200", "5. volume": "9988850"}, "2021-09-16": {"1. open": "278.1395", "2. high": "296.8200", "3. low": "278.0000", "4. close": "293.2600", "5. volume": "5304198"}, "2021-09-15": {"1. open": "268.0966", "2. high": "279.4700", "3. low": "261.2800", "4. close": "279.0900", "5. volume": "4649087"}, "2021-09-14": {"1. open": "274.7550", "2. high": "282.2500", "3. low": "264.2000", "4. close": "269.0400", "5. volume": "3986809"}, "2021-09-13": {"1. open": "270.7900", "2. high": "280.0000", "3. low": "259.0100", "4. close": "278.0000", "5. volume": "4412363"}, "2021-09-10": {"1. open": "289.0100", "2. high": "294.2300", "3. low": "268.2500", "4. close": "270.4600", "5. volume": "6401786"}, "2021-09-09": {"1. open": "270.6006", "2. high": "291.2500", "3. low": "262.0900", "4. close": "289.6000", "5. volume": "6710594"}, "2021-09-08": {"1. open": "275.2500", "2. high": "276.5700", "3. low": "260.9300", "4. close": "274.3300", "5. volume": "6904140"}, "2021-09-07": {"1. open": "250.3529", "2. high": "271.0000", "3. low": "249.0993", "4. close": "262.7000", "5. volume": "5062165"}, "2021-09-03": {"1. open": "240.0000", "2. high": "254.1300", "3. low": "240.0000", "4. close": "247.2900", "5. volume": "4565239"}, "2021-09-02": {"1. open": "227.5200", "2. high": "245.3899", "3. low": "227.5200", "4. close": "239.8000", "5. volume": "4264196"}, "2021-09-01": {"1. open": "228.3272", "2. high": "228.6900", "3. low": "222.7500", "4. close": "226.8100", "5. volume": "2525794"}, "2021-08-31": {"1. open": "215.5357", "2. high": "230.3800", "3. low": "215.3181", "4. close": "229.1200", "5. volume": "3614317"}, "2021-08-30": {"1. open": "226.8700", "2. high": "228.0000", "3. low": "215.3300", "4. close": "215.6400", "5. volume": "3462527"}, "2021-08-27": {"1. open": "218.0558", "2. high": "224.4900", "3. low": "212.0900", "4. close": "223.1800", "5. volume": "2938482"}, "2021-08-26": {"1. open": "214.7700", "2. high": "219.9799", "3. low": "211.2500", "4. close": "216.7500", "5. volume": "2380652"}, "2021-08-25": {"1. open": "218.8500", "2. high": "223.8222", "3. low": "214.0900", "4. close": "214.1400", "5. volume": "3929423"}, "2021-08-24": {"1. open": "206.0600", "2. high": "220.6999", "3. low": "204.2001", "4. close": "219.4500", "5. volume": "5521843"}, "2021-08-23": {"1. open": "201.2416", "2. high": "206.4700", "3. low": "198.8840", "4. close": "202.9600", "5. volume": "4427818"}, "2021-08-20": {"1. open": "197.1500", "2. high": "208.6000", "3. low": "192.5100", "4. close": "195.6400", "5. volume": "6125590"}, "2021-08-19": {"1. open": "210.1500", "2. high": "213.9900", "3. low": "192.5100", "4. close": "193.8700", "5. volume": "7321658"}, "2021-08-18": {"1. open": "204.6000", "2. high": "220.1100", "3. low": "203.6000", "4. close": "212.2700", "5. volume": "8752041"}, "2021-08-17": {"1. open": "190.6500", "2. high": "208.4900", "3. low": "190.1600", "4. close": "200.1800", "5. volume": "7450227"}, "2021-08-16": {"1. open": "198.2000", "2. high": "213.8999", "3. low": "188.2800", "4. close": "200.8900", "5. volume": "10656052"}, "2021-08-13": {"1. open": "187.8150", "2. high": "205.1899", "3. low": "184.5000", "4. close": "203.2900", "5. volume": "14168487"}, "2021-08-12": {"1. open": "167.6800", "2. high": "186.1400", "3. low": "166.2500", "4. close": "178.1200", "5. volume": "14108167"}, "2021-08-11": {"1. open": "166.8200", "2. high": "172.0000", "3. low": "156.7700", "4. close": "171.2000", "5. volume": "17993626"}, "2021-08-10": {"1. open": "139.4900", "2. high": "140.6099", "3. low": "135.1001", "4. close": "135.6800", "5. volume": "5022979"}, "2021-08-09": {"1. open": "134.9000", "2. high": "140.0300", "3. low": "133.4782", "4. close": "137.1900", "5. volume": "3915585"}, "2021-08-06": {"1. open": "135.2900", "2. high": "139.5600", "3. low": "130.6600", "4. close": "132.1300", "5. volume": "4449963"}, "2021-08-05": {"1. open": "128.1400", "2. high": "137.4000", "3. low": "124.3000", "4. close": "133.1700", "5. volume": "5132253"}, "2021-08-04": {"1. open": "128.0100", "2. high": "133.4600", "3. low": "125.7600", "4. close": "127.9800", "5. volume": "1862066"}, "2021-08-03": {"1. open": "133.8134", "2. high": "139.4100", "3. low": "125.0600", "4. close": "128.6800", "5. volume": "3793934"}, "2021-08-02": {"1. open": "122.0000", "2. high": "134.1500", "3. low": "121.0000", "4. close": "133.4100", "5. volume": "4736552"}, "2021-07-30": {"1. open": "121.0500", "2. high": "125.2500", "3. low": "120.3600", "4. close": "120.7600", "5. volume": "1317666"}, "2021-07-29": {"1. open": "123.0000", "2. high": "127.4000", "3. low": "122.9900", "4. close": "123.8700", "5. volume": "2813405"}, "2021-07-28": {"1. open": "117.3100", "2. high": "122.6400", "3. low": "116.3768", "4. close": "121.7900", "5. volume": "1829233"}, "2021-07-27": {"1. open": "121.6500", "2. high": "123.6900", "3. low": "112.6038", "4. close": "115.7500", "5. volume": "2360296"}, "2021-07-26": {"1. open": "116.7900", "2. high": "123.5000", "3. low": "115.6000", "4. close": "121.8200", "5. volume": "1962100"}, "2021-07-23": {"1. open": "116.9200", "2. high": "118.7658", "3. low": "113.8100", "4. close": "116.5700", "5. volume": "1327318"}, "2021-07-22": {"1. open": "120.0000", "2. high": "120.7464", "3. low": "115.3000", "4. close": "116.9100", "5. volume": "1440150"}, "2021-07-21": {"1. open": "118.0500", "2. high": "121.9900", "3. low": "116.5800", "4. close": "119.1500", "5. volume": "2123855"}, "2021-07-20": {"1. open": "116.9200", "2. high": "118.3000", "3. low": "113.1400", "4. close": "117.6300", "5. volume": "1894488"}, "2021-07-19": {"1. open": "109.8300", "2. high": "115.3899", "3. low": "109.2000", "4. close": "115.2800", "5. volume": "2504073"}, "2021-07-16": {"1. open": "115.2900", "2. high": "115.9000", "3. low": "109.5149", "4. close": "113.7900", "5. volume": "2148650"}, "2021-07-15": {"1. open": "111.9650", "2. high": "114.2999", "3. low": "107.2600", "4. close": "113.0900", "5. volume": "3463275"}, "2021-07-14": {"1. open": "120.9950", "2. high": "120.9950", "3. low": "112.0200", "4. close": "113.1300", "5. volume": "3835977"}, "2021-07-13": {"1. open": "128.1200", "2. high": "129.0000", "3. low": "118.5301", "4. close": "119.3800", "5. volume": "5274179"}, "2021-07-12": {"1. open": "123.6214", "2. high": "130.9000", "3. low": "122.7600", "4. close": "129.9000", "5. volume": "6942325"}, "2021-07-09": {"1. open": "122.9500", "2. high": "123.2041", "3. low": "117.2200", "4. close": "120.0000", "5. volume": "3218369"}, "2021-07-08": {"1. open": "112.5700", "2. high": "121.6800", "3. low": "110.8200", "4. close": "119.7500", "5. volume": "2991350"}, "2021-07-07": {"1. open": "120.5000", "2. high": "121.5400", "3. low": "114.2200", "4. close": "117.4000", "5. volume": "2895235"}, "2021-07-06": {"1. open": "122.0400", "2. high": "123.4800", "3. low": "115.8938", "4. close": "120.0000", "5. volume": "3391593"}, "2021-07-02": {"1. open": "125.5481", "2. high": "127.8847", "3. low": "118.1650", "4. close": "121.2100", "5. volume": "4133606"}, "2021-07-01": {"1. open": "126.0000", "2. high": "130.8800", "3. low": "122.6800", "4. close": "123.9200", "5. volume": "5060789"}, "2021-06-30": {"1. open": "122.0000", "2. high": "134.3800", "3. low": "120.1100", "4. close": "124.9000", "5. volume": "10763535"}, "2021-06-29": {"1. open": "125.0000", "2. high": "125.5000", "3. low": "120.7700", "4. close": "122.9300", "5. volume": "2995538"}, "2021-06-28": {"1. open": "123.5331", "2. high": "126.9900", "3. low": "120.2600", "4. close": "123.8900", "5. volume": "4050954"}, "2021-06-25": {"1. open": "124.3958", "2. high": "125.0000", "3. low": "117.7700", "4. close": "122.2000", "5. volume": "4327959"}, "2021-06-24": {"1. open": "128.6319", "2. high": "134.5000", "3. low": "122.2800", "4. close": "123.4200", "5. volume": "8849813"}, "2021-06-23": {"1. open": "120.3000", "2. high": "125.7500", "3. low": "119.4074", "4. close": "125.1400", "5. volume": "5762243"}, "2021-06-22": {"1. open": "120.6000", "2. high": "123.3499", "3. low": "115.6900", "4. close": "119.6500", "5. volume": "5954865"}, "2021-06-21": {"1. open": "125.5000", "2. high": "125.7200", "3. low": "118.4260", "4. close": "121.3500", "5. volume": "4223314"}, "2021-06-18": {"1. open": "126.8000", "2. high": "128.4599", "3. low": "120.4200", "4. close": "123.8600", "5. volume": "5368486"}, "2021-06-17": {"1. open": "120.9496", "2. high": "128.3000", "3. low": "119.3600", "4. close": "126.3100", "5. volume": "9289259"}, "2021-06-16": {"1. open": "119.5268", "2. high": "122.0000", "3. low": "114.2000", "4. close": "119.0100", "5. volume": "8809212"}, "2021-06-15": {"1. open": "125.7700", "2. high": "126.9699", "3. low": "117.4300", "4. close": "123.0300", "5. volume": "7099302"}, "2021-06-14": {"1. open": "120.2600", "2. high": "134.8200", "3. low": "120.0000", "4. close": "124.6900", "5. volume": "16323875"}, "2021-06-11": {"1. open": "143.2800", "2. high": "143.6400", "3. low": "125.0000", "4. close": "125.5050", "5. volume": "10197659"}, "2021-06-10": {"1. open": "150.3900", "2. high": "155.8699", "3. low": "144.0000", "4. close": "146.4200", "5. volume": "3922069"}, "2021-06-09": {"1. open": "164.0700", "2. high": "167.4999", "3. low": "150.2800", "4. close": "152.4300", "5. volume": "4171125"}, "2021-06-08": {"1. open": "171.0000", "2. high": "182.0000", "3. low": "161.9200", "4. close": "162.0100", "5. volume": "3756258"}, "2021-06-07": {"1. open": "169.7217", "2. high": "178.0000", "3. low": "164.2000", "4. close": "170.0000", "5. volume": "3840486"}, "2021-06-04": {"1. open": "167.2210", "2. high": "191.8900", "3. low": "160.1100", "4. close": "164.0400", "5. volume": "6401361"}, "2021-06-03": {"1. open": "150.5000", "2. high": "172.2499", "3. low": "145.1500", "4. close": "164.8300", "5. volume": "6058748"}, "2021-06-02": {"1. open": "145.4900", "2. high": "159.8000", "3. low": "138.0800", "4. close": "157.1400", "5. volume": "2793497"}, "2021-06-01": {"1. open": "150.0000", "2. high": "155.2132", "3. low": "136.0000", "4. close": "144.4900", "5. volume": "3523095"}, "2021-05-28": {"1. open": "164.0000", "2. high": "164.4900", "3. low": "143.7100", "4. close": "148.2200", "5. volume": "5253135"}, "2021-05-27": {"1. open": "145.1600", "2. high": "171.8700", "3. low": "138.6200", "4. close": "166.8300", "5. volume": "5054138"}, "2021-05-26": {"1. open": "135.1800", "2. high": "149.5899", "3. low": "133.0000", "4. close": "146.5800", "5. volume": "3491440"}, "2021-05-25": {"1. open": "141.7600", "2. high": "146.7206", "3. low": "132.5600", "4. close": "133.7000", "5. volume": "2304354"}, "2021-05-24": {"1. open": "152.0700", "2. high": "164.6400", "3. low": "138.0000", "4. close": "139.7700", "5. volume": "4718622"}, "2021-05-21": {"1. open": "140.6000", "2. high": "156.2400", "3. low": "137.3846", "4. close": "153.8500", "5. volume": "4072529"}, "2021-05-20": {"1. open": "135.0000", "2. high": "145.4000", "3. low": "129.2600", "4. close": "139.0800", "5. volume": "4889219"}, "2021-05-19": {"1. open": "110.7500", "2. high": "136.7445", "3. low": "108.4100", "4. close": "132.9100", "5. volume": "6595343"}, "2021-05-18": {"1. open": "111.6900", "2. high": "124.9000", "3. low": "111.4100", "4. close": "119.4900", "5. volume": "5006076"}, "2021-05-17": {"1. open": "100.0100", "2. high": "115.8999", "3. low": "96.0100", "4. close": "115.0000", "5. volume": "4924951"}, "2021-05-14": {"1. open": "87.7600", "2. high": "103.9500", "3. low": "86.2501", "4. close": "103.3600", "5. volume": "4400689"}, "2021-05-13": {"1. open": "96.2500", "2. high": "97.8700", "3. low": "80.8501", "4. close": "84.0500", "5. volume": "5638182"}, "2021-05-12": {"1. open": "115.2800", "2. high": "115.4765", "3. low": "88.8800", "4. close": "91.8200", "5. volume": "12764673"}, "2021-05-11": {"1. open": "83.4300", "2. high": "89.4900", "3. low": "81.2000", "4. close": "89.4400", "5. volume": "3806655"}, "2021-05-10": {"1. open": "93.0500", "2. high": "94.5699", "3. low": "86.2100", "4. close": "88.2100", "5. volume": "2291282"}, "2021-05-07": {"1. open": "96.4687", "2. high": "100.8599", "3. low": "94.2000", "4. close": "95.9700", "5. volume": "1648158"}, "2021-05-06": {"1. open": "97.2600", "2. high": "98.0000", "3. low": "88.3800", "4. close": "92.0400", "5. volume": "2312447"}, "2021-05-05": {"1. open": "109.1478", "2. high": "109.1478", "3. low": "97.5000", "4. close": "98.1900", "5. volume": "1387381"}, "2021-05-04": {"1. open": "115.0000", "2. high": "115.0000", "3. low": "101.1000", "4. close": "107.3600", "5. volume": "2081743"}, "2021-05-03": {"1. open": "111.1200", "2. high": "117.9900", "3. low": "105.7300", "4. close": "114.2000", "5. volume": "1773481"}, "2021-04-30": {"1. open": "103.9000", "2. high": "112.5000", "3. low": "103.6800", "4. close": "109.0200", "5. volume": "1199530"}, "2021-04-29": {"1. open": "115.7000", "2. high": "116.0000", "3. low": "103.0000", "4. close": "108.5600", "5. volume": "2145302"}, "2021-04-28": {"1. open": "116.9300", "2. high": "120.4600", "3. low": "111.2390", "4. close": "113.7500", "5. volume": "1648323"}, "2021-04-27": {"1. open": "114.9400", "2. high": "123.0879", "3. low": "112.3000", "4. close": "116.3300", "5. volume": "2629879"}, "2021-04-26": {"1. open": "108.8093", "2. high": "114.8000", "3. low": "108.0100", "4. close": "111.2400", "5. volume": "1936438"}, "2021-04-23": {"1. open": "102.9800", "2. high": "111.9500", "3. low": "102.4600", "4. close": "107.3800", "5. volume": "2120344"}, "2021-04-22": {"1. open": "102.5000", "2. high": "108.3000", "3. low": "99.2300", "4. close": "101.4400", "5. volume": "2104563"}, "2021-04-21": {"1. open": "91.4000", "2. high": "101.3400", "3. low": "89.3300", "4. close": "100.6100", "5. volume": "1713111"}, "2021-04-20": {"1. open": "96.3300", "2. high": "101.0000", "3. low": "90.3753", "4. close": "91.7900", "5. volume": "1626178"}, "2021-04-19": {"1. open": "104.4200", "2. high": "104.4200", "3. low": "93.6224", "4. close": "97.5500", "5. volume": "2723645"}, "2021-04-16": {"1. open": "111.0800", "2. high": "111.2299", "3. low": "103.0001", "4. close": "104.6500", "5. volume": "1584794"}, "2021-04-15": {"1. open": "109.2900", "2. high": "116.9600", "3. low": "105.6900", "4. close": "110.4000", "5. volume": "2347314"}, "2021-04-14": {"1. open": "110.2300", "2. high": "115.5599", "3. low": "104.3000", "4. close": "104.5100", "5. volume": "2062503"}, "2021-04-13": {"1. open": "111.8800", "2. high": "114.2700", "3. low": "102.6900", "4. close": "110.4600", "5. volume": "3733059"}, "2021-04-12": {"1. open": "127.7500", "2. high": "127.9500", "3. low": "111.2000", "4. close": "112.4600", "5. volume": "2891054"}, "2021-04-09": {"1. open": "122.0000", "2. high": "134.0000", "3. low": "118.0000", "4. close": "127.2900", "5. volume": "4545446"}, "2021-04-08": {"1. open": "128.5100", "2. high": "128.9800", "3. low": "119.1801", "4. close": "123.3300", "5. volume": "2548890"}, "2021-04-07": {"1. open": "136.5500", "2. high": "138.9700", "3. low": "123.8100", "4. close": "126.0700", "5. volume": "2674534"}, "2021-04-06": {"1. open": "140.2900", "2. high": "145.7800", "3. low": "138.0600", "4. close": "144.3000", "5. volume": "1018706"}, "2021-04-05": {"1. open": "147.7080", "2. high": "156.2699", "3. low": "136.0000", "4. close": "140.5200", "5. volume": "2029189"}, "2021-04-01": {"1. open": "133.9400", "2. high": "147.4799", "3. low": "133.0000", "4. close": "144.2800", "5. volume": "1871593"}, "2021-03-31": {"1. open": "131.6300", "2. high": "137.7878", "3. low": "128.0000", "4. close": "128.8600", "5. volume": "1137727"}, "2021-03-30": {"1. open": "133.4800", "2. high": "137.6100", "3. low": "122.6000", "4. close": "129.2800", "5. volume": "1521903"}, "2021-03-29": {"1. open": "140.8000", "2. high": "156.9300", "3. low": "132.5301", "4. close": "134.4900", "5. volume": "2652448"}, "2021-03-26": {"1. open": "125.0000", "2. high": "144.8600", "3. low": "118.2500", "4. close": "142.9500", "5. volume": "3260354"}, "2021-03-25": {"1. open": "106.3000", "2. high": "130.3590", "3. low": "105.9500", "4. close": "123.7300", "5. volume": "3820893"}, "2021-03-24": {"1. open": "121.8787", "2. high": "134.1600", "3. low": "110.1100", "4. close": "112.2800", "5. volume": "5499431"}, "2021-03-23": {"1. open": "159.9743", "2. high": "164.0600", "3. low": "115.5800", "4. close": "118.4800", "5. volume": "11899112"}, "2021-03-22": {"1. open": "127.9400", "2. high": "165.6600", "3. low": "124.0544", "4. close": "164.8700", "5. volume": "8566559"}, "2021-03-19": {"1. open": "108.0000", "2. high": "128.8000", "3. low": "106.5971", "4. close": "125.2800", "5. volume": "8696401"}, "2021-03-18": {"1. open": "83.5400", "2. high": "124.7500", "3. low": "81.9600", "4. close": "115.0900", "5. volume": "20944102"}, "2021-03-17": {"1. open": "56.7750", "2. high": "62.2600", "3. low": "54.5000", "4. close": "60.7900", "5. volume": "2762873"}, "2021-03-16": {"1. open": "62.2700", "2. high": "64.5000", "3. low": "56.8500", "4. close": "60.0500", "5. volume": "1266420"}, "2021-03-15": {"1. open": "58.8900", "2. high": "63.0100", "3. low": "56.8300", "4. close": "62.9300", "5. volume": "1434831"}, "2021-03-12": {"1. open": "53.5000", "2. high": "58.5000", "3. low": "53.5000", "4. close": "58.0000", "5. volume": "1130195"}, "2021-03-11": {"1. open": "54.7500", "2. high": "59.5500", "3. low": "54.0500", "4. close": "59.2400", "5. volume": "1260699"}, "2021-03-10": {"1. open": "57.3000", "2. high": "58.5500", "3. low": "52.1200", "4. close": "52.9900", "5. volume": "1540877"}, "2021-03-09": {"1. open": "49.3950", "2. high": "55.4500", "3. low": "49.0500", "4. close": "53.2400", "5. volume": "2035157"}, "2021-03-08": {"1. open": "50.6663", "2. high": "52.2227", "3. low": "45.1423", "4. close": "46.8700", "5. volume": "1382279"}, "2021-03-05": {"1. open": "54.5400", "2. high": "55.2900", "3. low": "42.5105", "4. close": "51.1600", "5. volume": "2322120"}, "2021-03-04": {"1. open": "56.1500", "2. high": "59.5450", "3. low": "49.0900", "4. close": "54.9200", "5. volume": "2218934"}, "2021-03-03": {"1. open": "61.7000", "2. high": "63.0050", "3. low": "55.6001", "4. close": "57.5800", "5. volume": "1610341"}, "2021-03-02": {"1. open": "67.2100", "2. high": "67.7600", "3. low": "58.2900", "4. close": "60.3600", "5. volume": "1772288"}, "2021-03-01": {"1. open": "66.7800", "2. high": "73.4600", "3. low": "65.8700", "4. close": "66.6500", "5. volume": "1315048"}, "2021-02-26": {"1. open": "68.7900", "2. high": "71.8800", "3. low": "63.3500", "4. close": "65.6400", "5. volume": "1551729"}, "2021-02-25": {"1. open": "74.0800", "2. high": "79.6200", "3. low": "66.0800", "4. close": "68.5200", "5. volume": "1411365"}, "2021-02-24": {"1. open": "73.7400", "2. high": "83.2900", "3. low": "72.0100", "4. close": "74.5100", "5. volume": "985584"}, "2021-02-23": {"1. open": "72.9500", "2. high": "75.3800", "3. low": "61.0100", "4. close": "73.0600", "5. volume": "1703111"}, "2021-02-22": {"1. open": "87.3000", "2. high": "89.4900", "3. low": "75.0600", "4. close": "77.0100", "5. volume": "1073238"}, "2021-02-19": {"1. open": "83.7500", "2. high": "93.0000", "3. low": "83.5000", "4. close": "89.7300", "5. volume": "753732"}, "2021-02-18": {"1. open": "84.0000", "2. high": "84.5200", "3. low": "78.5000", "4. close": "82.3200", "5. volume": "1016577"}, "2021-02-17": {"1. open": "91.7500", "2. high": "92.2686", "3. low": "84.1351", "4. close": "87.2400", "5. volume": "938501"}, "2021-02-16": {"1. open": "104.7700", "2. high": "105.0000", "3. low": "90.2702", "4. close": "92.2800", "5. volume": "1053900"}, "2021-02-12": {"1. open": "93.0000", "2. high": "102.2100", "3. low": "92.6200", "4. close": "102.1800", "5. volume": "646025"}, "2021-02-11": {"1. open": "93.5000", "2. high": "105.5800", "3. low": "92.5500", "4. close": "95.1300", "5. volume": "1432969"}, "2021-02-10": {"1. open": "80.9100", "2. high": "91.3900", "3. low": "78.7100", "4. close": "91.0400", "5. volume": "1076068"}, "2021-02-09": {"1. open": "75.9200", "2. high": "82.7500", "3. low": "75.5166", "4. close": "80.2500", "5. volume": "900418"}, "2021-02-08": {"1. open": "77.3400", "2. high": "78.3400", "3. low": "74.1000", "4. close": "76.0000", "5. volume": "713307"}, "2021-02-05": {"1. open": "76.1400", "2. high": "79.7800", "3. low": "74.0100", "4. close": "75.2400", "5. volume": "542316"}, "2021-02-04": {"1. open": "80.5500", "2. high": "81.0900", "3. low": "74.1900", "4. close": "75.7500", "5. volume": "720152"}, "2021-02-03": {"1. open": "76.9300", "2. high": "81.9100", "3. low": "76.5100", "4. close": "79.7500", "5. volume": "854626"}, "2021-02-02": {"1. open": "71.0400", "2. high": "80.0000", "3. low": "71.0400", "4. close": "75.4700", "5. volume": "1058596"}, "2021-02-01": {"1. open": "63.0000", "2. high": "70.8500", "3. low": "61.9000", "4. close": "70.2500", "5. volume": "812960"}, "2021-01-29": {"1. open": "64.5600", "2. high": "67.4000", "3. low": "60.1200", "4. close": "62.1900", "5. volume": "721699"}, "2021-01-28": {"1. open": "64.5400", "2. high": "67.4125", "3. low": "63.5200", "4. close": "65.1500", "5. volume": "617802"}, "2021-01-27": {"1. open": "60.0700", "2. high": "70.8000", "3. low": "58.0000", "4. close": "64.7000", "5. volume": "1398431"}, "2021-01-26": {"1. open": "67.7100", "2. high": "68.6900", "3. low": "63.3000", "4. close": "64.4500", "5. volume": "1506598"}, "2021-01-25": {"1. open": "65.0000", "2. high": "72.6700", "3. low": "64.0100", "4. close": "67.3600", "5. volume": "1781029"}, "2021-01-22": {"1. open": "62.4000", "2. high": "64.8800", "3. low": "58.5300", "4. close": "64.4700", "5. volume": "1241616"}, "2021-01-21": {"1. open": "55.0500", "2. high": "65.2900", "3. low": "55.0500", "4. close": "63.7700", "5. volume": "1702374"}, "2021-01-20": {"1. open": "54.5100", "2. high": "56.2200", "3. low": "53.2500", "4. close": "55.2200", "5. volume": "935527"}, "2021-01-19": {"1. open": "58.1300", "2. high": "61.6300", "3. low": "53.0000", "4. close": "54.2800", "5. volume": "1872415"}, "2021-01-15": {"1. open": "60.6400", "2. high": "62.6000", "3. low": "55.6000", "4. close": "56.0000", "5. volume": "1409538"}, "2021-01-14": {"1. open": "60.9200", "2. high": "67.4297", "3. low": "59.4900", "4. close": "60.6400", "5. volume": "1288652"}, "2021-01-13": {"1. open": "60.6100", "2. high": "69.4800", "3. low": "57.7000", "4. close": "57.8800", "5. volume": "1785613"}, "2021-01-12": {"1. open": "56.1100", "2. high": "63.5000", "3. low": "55.5300", "4. close": "62.4800", "5. volume": "1828232"}, "2021-01-11": {"1. open": "51.0000", "2. high": "56.0000", "3. low": "50.5300", "4. close": "54.7100", "5. volume": "1338175"}, "2021-01-08": {"1. open": "58.0000", "2. high": "58.0000", "3. low": "50.2800", "4. close": "52.7300", "5. volume": "1407739"}, "2021-01-07": {"1. open": "55.9900", "2. high": "61.2600", "3. low": "55.0400", "4. close": "55.3900", "5. volume": "1518920"}, "2021-01-06": {"1. open": "47.0500", "2. high": "57.0000", "3. low": "45.1400", "4. close": "52.1400", "5. volume": "2903194"}, "2021-01-05": {"1. open": "45.1000", "2. high": "53.6300", "3. low": "44.2001", "4. close": "48.3700", "5. volume": "3590669"}, "2021-01-04": {"1. open": "40.3400", "2. high": "45.0000", "3. low": "38.0500", "4. close": "43.9900", "5. volume": "1347052"}, "2020-12-31": {"1. open": "38.2000", "2. high": "40.9500", "3. low": "36.2600", "4. close": "40.7500", "5. volume": "969034"}, "2020-12-30": {"1. open": "41.2000", "2. high": "41.5000", "3. low": "38.1101", "4. close": "38.8700", "5. volume": "1049533"}, "2020-12-29": {"1. open": "42.0400", "2. high": "42.4900", "3. low": "39.5100", "4. close": "40.7500", "5. volume": "646398"}, "2020-12-28": {"1. open": "44.3100", "2. high": "45.0000", "3. low": "38.0500", "4. close": "42.6300", "5. volume": "1876812"}, "2020-12-24": {"1. open": "46.5900", "2. high": "47.4700", "3. low": "42.5051", "4. close": "43.9600", "5. volume": "873425"}, "2020-12-23": {"1. open": "47.5000", "2. high": "51.3984", "3. low": "43.0200", "4. close": "46.3200", "5. volume": "3142408"}, "2020-12-22": {"1. open": "43.1000", "2. high": "48.0800", "3. low": "40.6500", "4. close": "47.8400", "5. volume": "3731347"}, "2020-12-21": {"1. open": "44.0000", "2. high": "47.9900", "3. low": "40.0000", "4. close": "41.1000", "5. volume": "2833826"}, "2020-12-18": {"1. open": "38.0200", "2. high": "48.6600", "3. low": "37.0600", "4. close": "44.0900", "5. volume": "7266463"}, "2020-12-17": {"1. open": "28.6431", "2. high": "39.8500", "3. low": "28.2500", "4. close": "35.7700", "5. volume": "7042150"}, "2020-12-16": {"1. open": "26.0000", "2. high": "30.0100", "3. low": "22.6100", "4. close": "29.4700", "5. volume": "13459751"}}}